{
  "_meta": {
    "auto_generated": true,
    "generated_by": "python3/src/stock_ticker/hugo_generators.py :: generate_filtered_data()",
    "generated_at": "2026-05-26T19:02:05.824172",
    "warning": "DO NOT EDIT - This file is automatically generated and will be overwritten"
  },
  "generated_at": "2026-05-26T19:02:05.824186",
  "date": "2026-05-26",
  "pass1_extraction": {
    "total_attempted": 5875,
    "successful": 5539,
    "failed": 336,
    "success_rate": "94.3%"
  },
  "pass2_extraction": {
    "total_attempted": 5539,
    "successful": 3154,
    "pending": 2385
  }
}