{
  "_meta": {
    "auto_generated": true,
    "generated_by": "python3/src/stock_ticker/hugo_generators.py :: generate_filtered_data()",
    "generated_at": "2026-07-16T17:48:41.738128",
    "warning": "DO NOT EDIT - This file is automatically generated and will be overwritten"
  },
  "generated_at": "2026-07-16T17:48:41.738161",
  "date": "2026-07-16",
  "pass1_extraction": {
    "total_attempted": 6019,
    "successful": 5567,
    "failed": 452,
    "success_rate": "92.5%"
  },
  "pass2_extraction": {
    "total_attempted": 5567,
    "successful": 3108,
    "pending": 2459
  }
}