{
  "_meta": {
    "auto_generated": true,
    "generated_by": "python3/src/stock_ticker/hugo_generators.py :: generate_strategy_filters()",
    "generated_at": "2026-04-01T20:24:24.451443",
    "warning": "DO NOT EDIT - This file is automatically generated and will be overwritten"
  },
  "strategy": "Falling Knife",
  "strategy_key": "falling_knife",
  "description": "Oversold stocks below 200-day moving average (RSI < 30, price < MA200)",
  "icon": "\ud83d\udd2a",
  "generated_at": "2026-04-01T20:24:24.451455",
  "date": "2026-04-01",
  "total_matches": 136,
  "filter_criteria": "rsi_14 < 30 AND ma_200 IS NOT NULL AND price < ma_200",
  "tickers": [
    {
      "symbol": "MMS",
      "name": "Maximus, Inc. Common Stock",
      "exchange": "NYSE",
      "sector": "Industrials",
      "industry": "Specialty Business Services",
      "price": 62.56,
      "volume": 579641,
      "marketCap": 3412559104,
      "dividendYield": 206.0,
      "beta": 0.56,
      "rsi": 10.7,
      "ma200": 81.3,
      "ma50": 77.55,
      "peRatio": 9.6,
      "forwardPE": 6.86,
      "priceToBook": 1.98,
      "week52High": 100.0,
      "week52Low": 62.51,
      "scores": {
        "dividendDaddy": 68,
        "moonShot": 76,
        "fallingKnife": 95,
        "overHyped": null,
        "instWhale": 51
      }
    },
    {
      "symbol": "APPF",
      "name": "AppFolio, Inc. - Class A Common Stock",
      "exchange": "NASDAQ",
      "sector": "Technology",
      "industry": "Software - Application",
      "price": 154.14,
      "volume": 390665,
      "marketCap": 5547487232,
      "dividendYield": null,
      "beta": 0.8,
      "rsi": 10.9,
      "ma200": 232.42,
      "ma50": 180.58,
      "peRatio": 39.73,
      "forwardPE": 19.37,
      "priceToBook": 10.22,
      "week52High": 326.04,
      "week52Low": 152.81,
      "scores": {
        "dividendDaddy": 37,
        "moonShot": 84,
        "fallingKnife": 97,
        "overHyped": null,
        "instWhale": 62
      }
    },
    {
      "symbol": "SJM",
      "name": "The J.M. Smucker Company Common Stock",
      "exchange": "NYSE",
      "sector": "Consumer Defensive",
      "industry": "Packaged Foods",
      "price": 95.49,
      "volume": 1810079,
      "marketCap": 10188240896,
      "dividendYield": 456.0,
      "beta": 0.18,
      "rsi": 11.0,
      "ma200": 103.42,
      "ma50": 105.36,
      "peRatio": null,
      "forwardPE": 9.5,
      "priceToBook": 1.95,
      "week52High": 120.76,
      "week52Low": 93.3,
      "scores": {
        "dividendDaddy": 86,
        "moonShot": 52,
        "fallingKnife": 90,
        "overHyped": null,
        "instWhale": 73
      }
    },
    {
      "symbol": "MKTX",
      "name": "MarketAxess Holdings, Inc. - Common Stock",
      "exchange": "NASDAQ",
      "sector": "Financial Services",
      "industry": "Capital Markets",
      "price": 165.62,
      "volume": 408978,
      "marketCap": 6156344832,
      "dividendYield": 189.0,
      "beta": 0.97,
      "rsi": 11.4,
      "ma200": 181.25,
      "ma50": 174.96,
      "peRatio": 24.94,
      "forwardPE": 18.24,
      "priceToBook": 5.17,
      "week52High": 232.84,
      "week52Low": 156.17,
      "scores": {
        "dividendDaddy": 64,
        "moonShot": 88,
        "fallingKnife": 91,
        "overHyped": null,
        "instWhale": 64
      }
    },
    {
      "symbol": "MAZE",
      "name": "Maze Therapeutics, Inc. - Common Stock",
      "exchange": "NASDAQ",
      "sector": "Healthcare",
      "industry": "Biotechnology",
      "price": 29.05,
      "volume": 926812,
      "marketCap": 1433197696,
      "dividendYield": null,
      "beta": null,
      "rsi": 12.6,
      "ma200": 30.59,
      "ma50": 44.74,
      "peRatio": null,
      "forwardPE": -8.21,
      "priceToBook": 4.04,
      "week52High": 53.65,
      "week52Low": 6.71,
      "scores": {
        "dividendDaddy": 29,
        "moonShot": 39,
        "fallingKnife": 89,
        "overHyped": null,
        "instWhale": 32
      }
    },
    {
      "symbol": "LDOS",
      "name": "Leidos Holdings, Inc. Common Stock",
      "exchange": "NYSE",
      "sector": "Technology",
      "industry": "Information Technology Services",
      "price": 156.01,
      "volume": 852676,
      "marketCap": 19718522880,
      "dividendYield": 107.0,
      "beta": 0.62,
      "rsi": 14.1,
      "ma200": 178.68,
      "ma50": 175.26,
      "peRatio": 14.0,
      "forwardPE": 12.12,
      "priceToBook": 4.01,
      "week52High": 205.77,
      "week52Low": 128.32,
      "scores": {
        "dividendDaddy": 58,
        "moonShot": 75,
        "fallingKnife": 91,
        "overHyped": null,
        "instWhale": 82
      }
    },
    {
      "symbol": "CCSI",
      "name": "Consensus Cloud Solutions, Inc. - Common Stock",
      "exchange": "NASDAQ",
      "sector": "Technology",
      "industry": "Software - Infrastructure",
      "price": 23.67,
      "volume": 132591,
      "marketCap": 449866720,
      "dividendYield": null,
      "beta": 1.87,
      "rsi": 14.2,
      "ma200": 24.9,
      "ma50": 26.55,
      "peRatio": 5.44,
      "forwardPE": 4.01,
      "priceToBook": 32.6,
      "week52High": 31.66,
      "week52Low": 17.84,
      "scores": {
        "dividendDaddy": 7,
        "moonShot": 97,
        "fallingKnife": 89,
        "overHyped": null,
        "instWhale": 11
      }
    },
    {
      "symbol": "TBCH",
      "name": "Turtle Beach Corporation - Common Stock",
      "exchange": "NASDAQ",
      "sector": "Technology",
      "industry": "Consumer Electronics",
      "price": 10.22,
      "volume": 315174,
      "marketCap": 200312448,
      "dividendYield": null,
      "beta": 2.27,
      "rsi": 15.0,
      "ma200": 14.03,
      "ma50": 12.12,
      "peRatio": 13.27,
      "forwardPE": 6.91,
      "priceToBook": 1.53,
      "week52High": 17.39,
      "week52Low": 8.78,
      "scores": {
        "dividendDaddy": 3,
        "moonShot": 98,
        "fallingKnife": 96,
        "overHyped": null,
        "instWhale": 3
      }
    },
    {
      "symbol": "NXST",
      "name": "Nexstar Media Group, Inc. - Common Stock",
      "exchange": "NASDAQ",
      "sector": "Communication Services",
      "industry": "Broadcasting",
      "price": 179.3,
      "volume": 480901,
      "marketCap": 5437809664,
      "dividendYield": 411.0,
      "beta": 0.79,
      "rsi": 15.1,
      "ma200": 200.33,
      "ma50": 226.08,
      "peRatio": 59.77,
      "forwardPE": 10.0,
      "priceToBook": 2.63,
      "week52High": 254.3,
      "week52Low": 141.66,
      "scores": {
        "dividendDaddy": 82,
        "moonShot": 81,
        "fallingKnife": 90,
        "overHyped": null,
        "instWhale": 61
      }
    },
    {
      "symbol": "LNSR",
      "name": "LENSAR, Inc. - Common Stock",
      "exchange": "NASDAQ",
      "sector": "Healthcare",
      "industry": "Medical Devices",
      "price": 5.97,
      "volume": 166998,
      "marketCap": 71598208,
      "dividendYield": null,
      "beta": null,
      "rsi": 15.1,
      "ma200": 11.68,
      "ma50": 10.57,
      "peRatio": null,
      "forwardPE": -8.41,
      "priceToBook": -2.75,
      "week52High": 14.31,
      "week52Low": 5.35,
      "scores": {
        "dividendDaddy": 29,
        "moonShot": 36,
        "fallingKnife": 99,
        "overHyped": null,
        "instWhale": null
      }
    },
    {
      "symbol": "PRGS",
      "name": "Progress Software Corporation - Common Stock",
      "exchange": "NASDAQ",
      "sector": "Technology",
      "industry": "Software - Infrastructure",
      "price": 25.09,
      "volume": 1780340,
      "marketCap": 1056631424,
      "dividendYield": null,
      "beta": 0.57,
      "rsi": 15.8,
      "ma200": 43.65,
      "ma50": 37.18,
      "peRatio": 15.11,
      "forwardPE": 4.14,
      "priceToBook": 2.12,
      "week52High": 65.5,
      "week52Low": 23.82,
      "scores": {
        "dividendDaddy": 42,
        "moonShot": 71,
        "fallingKnife": 98,
        "overHyped": null,
        "instWhale": 26
      }
    },
    {
      "symbol": "WING",
      "name": "Wingstop Inc. - Common Stock",
      "exchange": "NASDAQ",
      "sector": "Consumer Cyclical",
      "industry": "Restaurants",
      "price": 144.87,
      "volume": 1494329,
      "marketCap": 4025481472,
      "dividendYield": 77.0,
      "beta": 1.86,
      "rsi": 16.0,
      "ma200": 269.64,
      "ma50": 231.19,
      "peRatio": 23.33,
      "forwardPE": 24.49,
      "priceToBook": -5.4,
      "week52High": 388.14,
      "week52Low": 144.68,
      "scores": {
        "dividendDaddy": 46,
        "moonShot": 97,
        "fallingKnife": 98,
        "overHyped": null,
        "instWhale": 55
      }
    },
    {
      "symbol": "BLKB",
      "name": "Blackbaud, Inc. - Common Stock",
      "exchange": "NASDAQ",
      "sector": "Technology",
      "industry": "Software - Application",
      "price": 37.55,
      "volume": 484748,
      "marketCap": 1796173440,
      "dividendYield": null,
      "beta": 1.11,
      "rsi": 16.2,
      "ma200": 59.32,
      "ma50": 47.36,
      "peRatio": 15.84,
      "forwardPE": 6.41,
      "priceToBook": 20.32,
      "week52High": 74.88,
      "week52Low": 37.33,
      "scores": {
        "dividendDaddy": 23,
        "moonShot": 89,
        "fallingKnife": 97,
        "overHyped": null,
        "instWhale": 37
      }
    },
    {
      "symbol": "JACK",
      "name": "Jack In The Box Inc. - Common Stock",
      "exchange": "NASDAQ",
      "sector": "Consumer Cyclical",
      "industry": "Restaurants",
      "price": 9.71,
      "volume": 1053456,
      "marketCap": 185491648,
      "dividendYield": 1571.0,
      "beta": 1.16,
      "rsi": 16.2,
      "ma200": 18.46,
      "ma50": 16.59,
      "peRatio": null,
      "forwardPE": 2.51,
      "priceToBook": -0.2,
      "week52High": 29.4,
      "week52Low": 8.92,
      "scores": {
        "dividendDaddy": 99,
        "moonShot": 90,
        "fallingKnife": 99,
        "overHyped": null,
        "instWhale": 3
      }
    },
    {
      "symbol": "TTAN",
      "name": "ServiceTitan, Inc. - Class A Common Stock",
      "exchange": "NASDAQ",
      "sector": "Technology",
      "industry": "Software - Application",
      "price": 62.43,
      "volume": 679421,
      "marketCap": 5947158016,
      "dividendYield": null,
      "beta": null,
      "rsi": 16.2,
      "ma200": 95.5,
      "ma50": 71.45,
      "peRatio": null,
      "forwardPE": 38.89,
      "priceToBook": 3.87,
      "week52High": 131.33,
      "week52Low": 58.01,
      "scores": {
        "dividendDaddy": 29,
        "moonShot": 34,
        "fallingKnife": 97,
        "overHyped": null,
        "instWhale": 63
      }
    },
    {
      "symbol": "NEXN",
      "name": "Nexxen International Ltd. - Ordinary Shares",
      "exchange": "NASDAQ",
      "sector": "Communication Services",
      "industry": "Advertising Agencies",
      "price": 6.53,
      "volume": 548605,
      "marketCap": 363856704,
      "dividendYield": null,
      "beta": 1.49,
      "rsi": 16.3,
      "ma200": 8.04,
      "ma50": 6.48,
      "peRatio": 15.93,
      "forwardPE": 5.4,
      "priceToBook": 0.77,
      "week52High": 12.6,
      "week52Low": 5.6,
      "scores": {
        "dividendDaddy": 14,
        "moonShot": 94,
        "fallingKnife": 93,
        "overHyped": null,
        "instWhale": 9
      }
    },
    {
      "symbol": "GLPI",
      "name": "Gaming and Leisure Properties, Inc. - Common Stock",
      "exchange": "NASDAQ",
      "sector": "Real Estate",
      "industry": "REIT - Specialty",
      "price": 44.31,
      "volume": 2514155,
      "marketCap": 12549560320,
      "dividendYield": 703.0,
      "beta": 0.68,
      "rsi": 17.0,
      "ma200": 44.55,
      "ma50": 46.06,
      "peRatio": 15.02,
      "forwardPE": 13.3,
      "priceToBook": 2.71,
      "week52High": 50.96,
      "week52Low": 41.17,
      "scores": {
        "dividendDaddy": 90,
        "moonShot": 76,
        "fallingKnife": 85,
        "overHyped": null,
        "instWhale": 76
      }
    },
    {
      "symbol": "SMX",
      "name": "SMX (Security Matters) Public Limited Company - Ordinary Shares",
      "exchange": "NASDAQ",
      "sector": "Industrials",
      "industry": "Specialty Business Services",
      "price": 8.42,
      "volume": 127340,
      "marketCap": 24376430,
      "dividendYield": null,
      "beta": -2.85,
      "rsi": 17.0,
      "ma200": 315.84,
      "ma50": 40.9,
      "peRatio": null,
      "forwardPE": null,
      "priceToBook": 1.71,
      "week52High": 3879.36,
      "week52Low": 5.1,
      "scores": {
        "dividendDaddy": 1,
        "moonShot": null,
        "fallingKnife": 100,
        "overHyped": null,
        "instWhale": null
      }
    },
    {
      "symbol": "PAR",
      "name": "PAR Technology Corporation Common Stock",
      "exchange": "NYSE",
      "sector": "Technology",
      "industry": "Software - Application",
      "price": 12.84,
      "volume": 1034257,
      "marketCap": 524807488,
      "dividendYield": null,
      "beta": 1.43,
      "rsi": 17.2,
      "ma200": 39.73,
      "ma50": 20.05,
      "peRatio": null,
      "forwardPE": 11.44,
      "priceToBook": 0.63,
      "week52High": 72.15,
      "week52Low": 12.42,
      "scores": {
        "dividendDaddy": 15,
        "moonShot": 93,
        "fallingKnife": 99,
        "overHyped": null,
        "instWhale": 14
      }
    },
    {
      "symbol": "FCPT",
      "name": "Four Corners Property Trust, Inc. Common Stock",
      "exchange": "NYSE",
      "sector": "Real Estate",
      "industry": "REIT - Retail",
      "price": 23.52,
      "volume": 319401,
      "marketCap": 2581203456,
      "dividendYield": 620.0,
      "beta": 0.83,
      "rsi": 17.3,
      "ma200": 24.13,
      "ma50": 24.53,
      "peRatio": 21.58,
      "forwardPE": 19.63,
      "priceToBook": 1.56,
      "week52High": 28.98,
      "week52Low": 22.78,
      "scores": {
        "dividendDaddy": 89,
        "moonShot": 81,
        "fallingKnife": 86,
        "overHyped": null,
        "instWhale": 44
      }
    },
    {
      "symbol": "OPCH",
      "name": "Option Care Health, Inc. - Common Stock",
      "exchange": "NASDAQ",
      "sector": "Healthcare",
      "industry": "Medical Care Facilities",
      "price": 26.49,
      "volume": 2006004,
      "marketCap": 4204829184,
      "dividendYield": null,
      "beta": 0.88,
      "rsi": 17.6,
      "ma200": 30.28,
      "ma50": 32.06,
      "peRatio": 20.86,
      "forwardPE": 12.46,
      "priceToBook": 3.13,
      "week52High": 36.8,
      "week52Low": 24.24,
      "scores": {
        "dividendDaddy": 35,
        "moonShot": 83,
        "fallingKnife": 90,
        "overHyped": null,
        "instWhale": 56
      }
    },
    {
      "symbol": "FUBO",
      "name": "FuboTV Inc. Class A Common Stock",
      "exchange": "NYSE",
      "sector": "Communication Services",
      "industry": "Broadcasting",
      "price": 9.2,
      "volume": 1787244,
      "marketCap": 270786656,
      "dividendYield": null,
      "beta": 2.28,
      "rsi": 18.9,
      "ma200": 35.38,
      "ma50": 16.94,
      "peRatio": 2.4,
      "forwardPE": 11.86,
      "priceToBook": 0.98,
      "week52High": 56.64,
      "week52Low": 8.31,
      "scores": {
        "dividendDaddy": 3,
        "moonShot": 98,
        "fallingKnife": 99,
        "overHyped": null,
        "instWhale": 5
      }
    },
    {
      "symbol": "THC",
      "name": "Tenet Healthcare Corporation Common Stock",
      "exchange": "NYSE",
      "sector": "Healthcare",
      "industry": "Medical Care Facilities",
      "price": 190.27,
      "volume": 688477,
      "marketCap": 16721879040,
      "dividendYield": null,
      "beta": 1.41,
      "rsi": 19.0,
      "ma200": 195.15,
      "ma50": 212.71,
      "peRatio": 12.28,
      "forwardPE": 10.84,
      "priceToBook": 3.92,
      "week52High": 247.21,
      "week52Low": 109.82,
      "scores": {
        "dividendDaddy": 16,
        "moonShot": 93,
        "fallingKnife": 85,
        "overHyped": 1,
        "instWhale": 80
      }
    },
    {
      "symbol": "WVE",
      "name": "Wave Life Sciences Ltd. - Ordinary Shares",
      "exchange": "NASDAQ",
      "sector": "Healthcare",
      "industry": "Biotechnology",
      "price": 6.83,
      "volume": 4540699,
      "marketCap": 1285781376,
      "dividendYield": null,
      "beta": -1.66,
      "rsi": 19.0,
      "ma200": 10.19,
      "ma50": 12.54,
      "peRatio": null,
      "forwardPE": -5.38,
      "priceToBook": 2.47,
      "week52High": 21.73,
      "week52Low": 5.02,
      "scores": {
        "dividendDaddy": 11,
        "moonShot": null,
        "fallingKnife": 96,
        "overHyped": 1,
        "instWhale": 30
      }
    },
    {
      "symbol": "SOJD",
      "name": "Southern Company (The) Series 2020A 4.95% Junior Subordinated Notes due January 30, 2080",
      "exchange": "NYSE",
      "sector": null,
      "industry": null,
      "price": 19.5,
      "volume": 108794,
      "marketCap": null,
      "dividendYield": null,
      "beta": null,
      "rsi": 19.5,
      "ma200": 20.24,
      "ma50": 20.41,
      "peRatio": null,
      "forwardPE": null,
      "priceToBook": null,
      "week52High": 22.4,
      "week52Low": 19.26,
      "scores": {
        "dividendDaddy": null,
        "moonShot": null,
        "fallingKnife": null,
        "overHyped": null,
        "instWhale": null
      }
    },
    {
      "symbol": "CDT",
      "name": "CDT Equity Inc. - Common Stock",
      "exchange": "NASDAQ",
      "sector": "Healthcare",
      "industry": "Biotechnology",
      "price": 5.1,
      "volume": 707228,
      "marketCap": 24084500,
      "dividendYield": null,
      "beta": 1.81,
      "rsi": 19.7,
      "ma200": 154.33,
      "ma50": 19.85,
      "peRatio": null,
      "forwardPE": null,
      "priceToBook": 0.06,
      "week52High": 4200.0,
      "week52Low": 4.4,
      "scores": {
        "dividendDaddy": 8,
        "moonShot": 96,
        "fallingKnife": 99,
        "overHyped": 1,
        "instWhale": null
      }
    },
    {
      "symbol": "RPD",
      "name": "Rapid7, Inc. - Common Stock",
      "exchange": "NASDAQ",
      "sector": "Technology",
      "industry": "Software - Infrastructure",
      "price": 5.44,
      "volume": 1304687,
      "marketCap": 358458528,
      "dividendYield": null,
      "beta": 0.89,
      "rsi": 19.8,
      "ma200": 16.02,
      "ma50": 8.01,
      "peRatio": 15.11,
      "forwardPE": 3.41,
      "priceToBook": 2.31,
      "week52High": 27.52,
      "week52Low": 5.24,
      "scores": {
        "dividendDaddy": 35,
        "moonShot": 82,
        "fallingKnife": 99,
        "overHyped": 1,
        "instWhale": 8
      }
    },
    {
      "symbol": "BIPC",
      "name": "Brookfield Infrastructure Corporation Brookfield Infrastructure Corporation",
      "exchange": "NYSE",
      "sector": "Utilities",
      "industry": "Utilities - Regulated Gas",
      "price": 39.54,
      "volume": 877651,
      "marketCap": 4839959552,
      "dividendYield": 461.0,
      "beta": 1.31,
      "rsi": 19.8,
      "ma200": 43.03,
      "ma50": 45.84,
      "peRatio": null,
      "forwardPE": 3.45,
      "priceToBook": -3.65,
      "week52High": 51.72,
      "week52Low": 32.08,
      "scores": {
        "dividendDaddy": 84,
        "moonShot": 91,
        "fallingKnife": 88,
        "overHyped": 1,
        "instWhale": 58
      }
    },
    {
      "symbol": "RLI",
      "name": "RLI Corp. Common Stock (DE)",
      "exchange": "NYSE",
      "sector": "Financial Services",
      "industry": "Insurance - Property & Casualty",
      "price": 56.94,
      "volume": 571416,
      "marketCap": 5234717696,
      "dividendYield": 112.0,
      "beta": 0.45,
      "rsi": 19.9,
      "ma200": 62.48,
      "ma50": 59.86,
      "peRatio": 13.03,
      "forwardPE": 19.9,
      "priceToBook": 2.94,
      "week52High": 81.79,
      "week52Low": 55.8,
      "scores": {
        "dividendDaddy": 59,
        "moonShot": 58,
        "fallingKnife": 88,
        "overHyped": 1,
        "instWhale": 60
      }
    },
    {
      "symbol": "VITL",
      "name": "Vital Farms, Inc. - Common Stock",
      "exchange": "NASDAQ",
      "sector": "Consumer Defensive",
      "industry": "Farm Products",
      "price": 13.4,
      "volume": 2980723,
      "marketCap": 600281472,
      "dividendYield": null,
      "beta": 1.21,
      "rsi": 20.3,
      "ma200": 34.25,
      "ma50": 21.95,
      "peRatio": 9.31,
      "forwardPE": 9.29,
      "priceToBook": 1.71,
      "week52High": 53.12,
      "week52Low": 12.63,
      "scores": {
        "dividendDaddy": 20,
        "moonShot": 89,
        "fallingKnife": 99,
        "overHyped": 1,
        "instWhale": 16
      }
    },
    {
      "symbol": "NVAX",
      "name": "Novavax, Inc. - Common Stock",
      "exchange": "NASDAQ",
      "sector": "Healthcare",
      "industry": "Biotechnology",
      "price": 8.02,
      "volume": 2776376,
      "marketCap": 1306746368,
      "dividendYield": null,
      "beta": 2.63,
      "rsi": 20.5,
      "ma200": 8.03,
      "ma50": 9.37,
      "peRatio": 3.11,
      "forwardPE": -10.38,
      "priceToBook": -10.2,
      "week52High": 11.97,
      "week52Low": 5.01,
      "scores": {
        "dividendDaddy": 2,
        "moonShot": 98,
        "fallingKnife": 83,
        "overHyped": 1,
        "instWhale": 30
      }
    },
    {
      "symbol": "JILL",
      "name": "J. Jill, Inc. Common Stock",
      "exchange": "NYSE",
      "sector": "Consumer Cyclical",
      "industry": "Apparel Retail",
      "price": 11.28,
      "volume": 452098,
      "marketCap": 167677648,
      "dividendYield": 279.0,
      "beta": null,
      "rsi": 20.5,
      "ma200": 15.68,
      "ma50": 16.03,
      "peRatio": 5.17,
      "forwardPE": 4.36,
      "priceToBook": 1.38,
      "week52High": 19.19,
      "week52Low": 10.4,
      "scores": {
        "dividendDaddy": 72,
        "moonShot": 30,
        "fallingKnife": 95,
        "overHyped": 1,
        "instWhale": 2
      }
    },
    {
      "symbol": "VRDN",
      "name": "Viridian Therapeutics, Inc.  - Common Stock",
      "exchange": "NASDAQ",
      "sector": "Healthcare",
      "industry": "Biotechnology",
      "price": 19.15,
      "volume": 2852291,
      "marketCap": 1957255680,
      "dividendYield": null,
      "beta": 1.01,
      "rsi": 20.8,
      "ma200": 24.44,
      "ma50": 28.99,
      "peRatio": null,
      "forwardPE": -8.81,
      "priceToBook": 3.3,
      "week52High": 34.29,
      "week52Low": 9.9,
      "scores": {
        "dividendDaddy": 26,
        "moonShot": 85,
        "fallingKnife": 93,
        "overHyped": 1,
        "instWhale": 38
      }
    },
    {
      "symbol": "IDCC",
      "name": "InterDigital, Inc. - Common Stock",
      "exchange": "NASDAQ",
      "sector": "Technology",
      "industry": "Software - Application",
      "price": 306.39,
      "volume": 276642,
      "marketCap": 7887873536,
      "dividendYield": 93.0,
      "beta": 1.59,
      "rsi": 21.2,
      "ma200": 315.88,
      "ma50": 345.16,
      "peRatio": 25.94,
      "forwardPE": 26.82,
      "priceToBook": 7.15,
      "week52High": 412.6,
      "week52Low": 180.6,
      "scores": {
        "dividendDaddy": 51,
        "moonShot": 94,
        "fallingKnife": 84,
        "overHyped": 1,
        "instWhale": 69
      }
    },
    {
      "symbol": "NHS",
      "name": "Neuberger High Yield Strategies Fund Inc. Common Stock",
      "exchange": "NYSE MKT",
      "sector": "Financial Services",
      "industry": "Asset Management",
      "price": 6.49,
      "volume": 279338,
      "marketCap": 203733056,
      "dividendYield": 1676.0,
      "beta": 0.75,
      "rsi": 21.4,
      "ma200": 6.97,
      "ma50": 7.2,
      "peRatio": 9.83,
      "forwardPE": null,
      "priceToBook": 0.87,
      "week52High": 7.8,
      "week52Low": 6.27,
      "scores": {
        "dividendDaddy": 99,
        "moonShot": 75,
        "fallingKnife": 86,
        "overHyped": 1,
        "instWhale": 3
      }
    },
    {
      "symbol": "FRPT",
      "name": "Freshpet, Inc. - Common Stock",
      "exchange": "NASDAQ",
      "sector": "Consumer Defensive",
      "industry": "Packaged Foods",
      "price": 60.08,
      "volume": 1708430,
      "marketCap": 2947355136,
      "dividendYield": null,
      "beta": 1.67,
      "rsi": 21.6,
      "ma200": 63.24,
      "ma50": 71.78,
      "peRatio": 22.76,
      "forwardPE": 29.83,
      "priceToBook": 2.43,
      "week52High": 89.8,
      "week52Low": 46.76,
      "scores": {
        "dividendDaddy": 10,
        "moonShot": 95,
        "fallingKnife": 85,
        "overHyped": 1,
        "instWhale": 47
      }
    },
    {
      "symbol": "DAVE",
      "name": "Dave Inc.  - Class A Common Stock",
      "exchange": "NASDAQ",
      "sector": "Technology",
      "industry": "Software - Application",
      "price": 173.45,
      "volume": 425028,
      "marketCap": 2299877120,
      "dividendYield": null,
      "beta": 3.87,
      "rsi": 21.6,
      "ma200": 209.34,
      "ma50": 188.78,
      "peRatio": 12.82,
      "forwardPE": 9.89,
      "priceToBook": 6.66,
      "week52High": 286.45,
      "week52Low": 65.46,
      "scores": {
        "dividendDaddy": null,
        "moonShot": 99,
        "fallingKnife": 91,
        "overHyped": 1,
        "instWhale": 42
      }
    },
    {
      "symbol": "SYY",
      "name": "Sysco Corporation Common Stock",
      "exchange": "NYSE",
      "sector": "Consumer Defensive",
      "industry": "Food Distribution",
      "price": 72.17,
      "volume": 9052469,
      "marketCap": 34564423680,
      "dividendYield": 303.0,
      "beta": 0.59,
      "rsi": 21.8,
      "ma200": 78.64,
      "ma50": 84.28,
      "peRatio": 19.45,
      "forwardPE": 14.36,
      "priceToBook": 15.14,
      "week52High": 91.85,
      "week52Low": 67.12,
      "scores": {
        "dividendDaddy": 76,
        "moonShot": 65,
        "fallingKnife": 87,
        "overHyped": 1,
        "instWhale": 87
      }
    },
    {
      "symbol": "DBX",
      "name": "Dropbox, Inc. - Class A Common Stock",
      "exchange": "NASDAQ",
      "sector": "Technology",
      "industry": "Software - Infrastructure",
      "price": 23.07,
      "volume": 3758503,
      "marketCap": 5777369600,
      "dividendYield": null,
      "beta": 0.59,
      "rsi": 21.8,
      "ma200": 27.76,
      "ma50": 25.02,
      "peRatio": 12.4,
      "forwardPE": 6.85,
      "priceToBook": -3.12,
      "week52High": 32.4,
      "week52Low": 22.0,
      "scores": {
        "dividendDaddy": 42,
        "moonShot": 65,
        "fallingKnife": 91,
        "overHyped": 1,
        "instWhale": 63
      }
    },
    {
      "symbol": "DUKB",
      "name": "Duke Energy Corporation 5.625% Junior Subordinated Debentures due 2078",
      "exchange": "NYSE",
      "sector": null,
      "industry": null,
      "price": 23.41,
      "volume": 102136,
      "marketCap": null,
      "dividendYield": null,
      "beta": null,
      "rsi": 21.8,
      "ma200": 23.92,
      "ma50": 24.21,
      "peRatio": null,
      "forwardPE": null,
      "priceToBook": null,
      "week52High": 25.3,
      "week52Low": 23.23,
      "scores": {
        "dividendDaddy": null,
        "moonShot": null,
        "fallingKnife": null,
        "overHyped": null,
        "instWhale": null
      }
    },
    {
      "symbol": "ADMA",
      "name": "ADMA Biologics Inc - Common Stock",
      "exchange": "NASDAQ",
      "sector": "Healthcare",
      "industry": "Biotechnology",
      "price": 9.11,
      "volume": 7773935,
      "marketCap": 2169629952,
      "dividendYield": null,
      "beta": 0.59,
      "rsi": 22.3,
      "ma200": 16.65,
      "ma50": 15.13,
      "peRatio": 15.18,
      "forwardPE": 6.6,
      "priceToBook": 4.54,
      "week52High": 25.67,
      "week52Low": 7.21,
      "scores": {
        "dividendDaddy": 41,
        "moonShot": 64,
        "fallingKnife": 98,
        "overHyped": 1,
        "instWhale": 41
      }
    },
    {
      "symbol": "NKE",
      "name": "Nike, Inc. Common Stock",
      "exchange": "NYSE",
      "sector": "Consumer Cyclical",
      "industry": "Footwear & Accessories",
      "price": 44.63,
      "volume": 113580907,
      "marketCap": 66069512192,
      "dividendYield": 310.0,
      "beta": 1.29,
      "rsi": 22.4,
      "ma200": 65.82,
      "ma50": 59.09,
      "peRatio": 26.1,
      "forwardPE": 22.9,
      "priceToBook": 4.99,
      "week52High": 80.17,
      "week52Low": 44.56,
      "scores": {
        "dividendDaddy": 74,
        "moonShot": 90,
        "fallingKnife": 96,
        "overHyped": 1,
        "instWhale": 92
      }
    },
    {
      "symbol": "GDYN",
      "name": "Grid Dynamics Holdings, Inc. - Class A Common Stock",
      "exchange": "NASDAQ",
      "sector": "Technology",
      "industry": "Information Technology Services",
      "price": 5.64,
      "volume": 1348259,
      "marketCap": 481395232,
      "dividendYield": null,
      "beta": 0.82,
      "rsi": 22.6,
      "ma200": 8.48,
      "ma50": 6.83,
      "peRatio": 51.27,
      "forwardPE": 10.67,
      "priceToBook": 0.88,
      "week52High": 15.88,
      "week52Low": 5.48,
      "scores": {
        "dividendDaddy": 36,
        "moonShot": 77,
        "fallingKnife": 96,
        "overHyped": 1,
        "instWhale": 12
      }
    },
    {
      "symbol": "DG",
      "name": "Dollar General Corporation Common Stock",
      "exchange": "NYSE",
      "sector": "Consumer Defensive",
      "industry": "Discount Stores",
      "price": 117.17,
      "volume": 2513965,
      "marketCap": 25803917312,
      "dividendYield": 199.0,
      "beta": 0.22,
      "rsi": 22.9,
      "ma200": 119.89,
      "ma50": 141.32,
      "peRatio": 17.11,
      "forwardPE": 14.69,
      "priceToBook": 3.03,
      "week52High": 158.23,
      "week52Low": 84.7,
      "scores": {
        "dividendDaddy": 69,
        "moonShot": 40,
        "fallingKnife": 83,
        "overHyped": 2,
        "instWhale": 85
      }
    },
    {
      "symbol": "IRT",
      "name": "Independence Realty Trust, Inc. Common Stock",
      "exchange": "NYSE",
      "sector": "Real Estate",
      "industry": "REIT - Residential",
      "price": 14.87,
      "volume": 2260323,
      "marketCap": 3616709888,
      "dividendYield": 457.0,
      "beta": 0.99,
      "rsi": 23.0,
      "ma200": 16.45,
      "ma50": 16.03,
      "peRatio": 61.96,
      "forwardPE": 61.96,
      "priceToBook": 1.02,
      "week52High": 21.56,
      "week52Low": 14.63,
      "scores": {
        "dividendDaddy": 84,
        "moonShot": 83,
        "fallingKnife": 87,
        "overHyped": 2,
        "instWhale": 52
      }
    },
    {
      "symbol": "MKC",
      "name": "McCormick & Company, Incorporated Common Stock",
      "exchange": "NYSE",
      "sector": "Consumer Defensive",
      "industry": "Packaged Foods",
      "price": 48.38,
      "volume": 11364615,
      "marketCap": 12987042816,
      "dividendYield": 381.0,
      "beta": null,
      "rsi": 23.0,
      "ma200": 66.51,
      "ma50": 62.56,
      "peRatio": 7.93,
      "forwardPE": 14.41,
      "priceToBook": 1.86,
      "week52High": 82.9,
      "week52Low": 48.05,
      "scores": {
        "dividendDaddy": 80,
        "moonShot": 27,
        "fallingKnife": 94,
        "overHyped": 2,
        "instWhale": 77
      }
    },
    {
      "symbol": "TRI",
      "name": "Thomson Reuters Corp - Common Shares",
      "exchange": "NASDAQ",
      "sector": "Industrials",
      "industry": "Specialty Business Services",
      "price": 88.05,
      "volume": 2913871,
      "marketCap": 39081279488,
      "dividendYield": 291.0,
      "beta": 0.17,
      "rsi": 23.1,
      "ma200": 144.8,
      "ma50": 97.66,
      "peRatio": 26.76,
      "forwardPE": 17.49,
      "priceToBook": 3.32,
      "week52High": 218.42,
      "week52Low": 79.71,
      "scores": {
        "dividendDaddy": 77,
        "moonShot": 36,
        "fallingKnife": 97,
        "overHyped": 2,
        "instWhale": 89
      }
    },
    {
      "symbol": "CTAS",
      "name": "Cintas Corporation - Common Stock",
      "exchange": "NASDAQ",
      "sector": "Industrials",
      "industry": "Specialty Business Services",
      "price": 172.04,
      "volume": 2961573,
      "marketCap": 68821491712,
      "dividendYield": 106.0,
      "beta": 0.94,
      "rsi": 23.4,
      "ma200": 198.26,
      "ma50": 191.34,
      "peRatio": 36.3,
      "forwardPE": 31.71,
      "priceToBook": 14.37,
      "week52High": 229.24,
      "week52Low": 165.6,
      "scores": {
        "dividendDaddy": 56,
        "moonShot": 81,
        "fallingKnife": 89,
        "overHyped": 2,
        "instWhale": 92
      }
    },
    {
      "symbol": "PTC",
      "name": "PTC Inc. - Common Stock",
      "exchange": "NASDAQ",
      "sector": "Technology",
      "industry": "Software - Application",
      "price": 142.52,
      "volume": 753982,
      "marketCap": 16959326208,
      "dividendYield": null,
      "beta": 1.04,
      "rsi": 23.4,
      "ma200": 182.07,
      "ma50": 154.85,
      "peRatio": 20.96,
      "forwardPE": 17.23,
      "priceToBook": 4.41,
      "week52High": 219.69,
      "week52Low": 133.38,
      "scores": {
        "dividendDaddy": 24,
        "moonShot": 84,
        "fallingKnife": 92,
        "overHyped": 2,
        "instWhale": 80
      }
    },
    {
      "symbol": "AVNW",
      "name": "Aviat Networks, Inc. - Common Stock",
      "exchange": "NASDAQ",
      "sector": "Technology",
      "industry": "Communication Equipment",
      "price": 19.67,
      "volume": 894783,
      "marketCap": 253788432,
      "dividendYield": null,
      "beta": 0.8,
      "rsi": 23.5,
      "ma200": 23.04,
      "ma50": 24.3,
      "peRatio": 17.41,
      "forwardPE": 6.2,
      "priceToBook": 0.93,
      "week52High": 27.02,
      "week52Low": 15.8,
      "scores": {
        "dividendDaddy": 37,
        "moonShot": 75,
        "fallingKnife": 89,
        "overHyped": 2,
        "instWhale": 5
      }
    },
    {
      "symbol": "MAT",
      "name": "Mattel, Inc. - Common Stock",
      "exchange": "NASDAQ",
      "sector": "Consumer Cyclical",
      "industry": "Leisure",
      "price": 14.56,
      "volume": 4512478,
      "marketCap": 4525248000,
      "dividendYield": null,
      "beta": 0.73,
      "rsi": 23.6,
      "ma200": 18.61,
      "ma50": 17.42,
      "peRatio": 11.74,
      "forwardPE": 9.48,
      "priceToBook": 1.97,
      "week52High": 22.48,
      "week52Low": 13.95,
      "scores": {
        "dividendDaddy": 39,
        "moonShot": 71,
        "fallingKnife": 92,
        "overHyped": 2,
        "instWhale": 57
      }
    },
    {
      "symbol": "CACC",
      "name": "Credit Acceptance Corporation - Common Stock",
      "exchange": "NASDAQ",
      "sector": "Financial Services",
      "industry": "Credit Services",
      "price": 419.6,
      "volume": 211338,
      "marketCap": 4628836352,
      "dividendYield": null,
      "beta": 1.3,
      "rsi": 23.7,
      "ma200": 479.26,
      "ma50": 472.64,
      "peRatio": 11.53,
      "forwardPE": 7.72,
      "priceToBook": 2.94,
      "week52High": 549.75,
      "week52Low": 401.9,
      "scores": {
        "dividendDaddy": 18,
        "moonShot": 90,
        "fallingKnife": 88,
        "overHyped": 2,
        "instWhale": 58
      }
    },
    {
      "symbol": "CERT",
      "name": "Certara, Inc. - Common Stock",
      "exchange": "NASDAQ",
      "sector": "Healthcare",
      "industry": "Health Information Services",
      "price": 5.5,
      "volume": 5746357,
      "marketCap": 876003456,
      "dividendYield": null,
      "beta": 1.58,
      "rsi": 24.0,
      "ma200": 9.7,
      "ma50": 7.18,
      "peRatio": null,
      "forwardPE": 11.03,
      "priceToBook": 0.82,
      "week52High": 15.38,
      "week52Low": 5.38,
      "scores": {
        "dividendDaddy": 12,
        "moonShot": 93,
        "fallingKnife": 98,
        "overHyped": 2,
        "instWhale": 23
      }
    },
    {
      "symbol": "TENB",
      "name": "Tenable Holdings, Inc. - Common Stock",
      "exchange": "NASDAQ",
      "sector": "Technology",
      "industry": "Software - Infrastructure",
      "price": 17.05,
      "volume": 2625424,
      "marketCap": 2034819584,
      "dividendYield": null,
      "beta": 0.71,
      "rsi": 24.0,
      "ma200": 26.88,
      "ma50": 20.45,
      "peRatio": null,
      "forwardPE": 8.2,
      "priceToBook": 6.19,
      "week52High": 35.69,
      "week52Low": 15.85,
      "scores": {
        "dividendDaddy": 39,
        "moonShot": 70,
        "fallingKnife": 97,
        "overHyped": 2,
        "instWhale": 39
      }
    },
    {
      "symbol": "CELH",
      "name": "Celsius Holdings, Inc. - Common Stock",
      "exchange": "NASDAQ",
      "sector": "Consumer Defensive",
      "industry": "Beverages - Non-Alcoholic",
      "price": 34.33,
      "volume": 5980275,
      "marketCap": 8849769472,
      "dividendYield": null,
      "beta": 0.96,
      "rsi": 24.2,
      "ma200": 49.72,
      "ma50": 46.06,
      "peRatio": 137.32,
      "forwardPE": 16.73,
      "priceToBook": 7.46,
      "week52High": 66.74,
      "week52Low": 32.36,
      "scores": {
        "dividendDaddy": 33,
        "moonShot": 81,
        "fallingKnife": 95,
        "overHyped": 2,
        "instWhale": 71
      }
    },
    {
      "symbol": "USAR",
      "name": "USA Rare Earth, Inc. - Common Stock",
      "exchange": "NASDAQ",
      "sector": "Basic Materials",
      "industry": "Other Industrial Metals & Mining",
      "price": 14.8,
      "volume": 11427124,
      "marketCap": 3226047488,
      "dividendYield": null,
      "beta": 1.08,
      "rsi": 24.2,
      "ma200": 17.28,
      "ma50": 19.87,
      "peRatio": null,
      "forwardPE": -47.74,
      "priceToBook": 4.45,
      "week52High": 43.98,
      "week52Low": 6.17,
      "scores": {
        "dividendDaddy": 23,
        "moonShot": 85,
        "fallingKnife": 89,
        "overHyped": 2,
        "instWhale": 50
      }
    },
    {
      "symbol": "RNAC",
      "name": "Cartesian Therapeutics, Inc. - Common Stock",
      "exchange": "NASDAQ",
      "sector": "Healthcare",
      "industry": "Biotechnology",
      "price": 6.39,
      "volume": 103739,
      "marketCap": 169392656,
      "dividendYield": null,
      "beta": 0.23,
      "rsi": 24.2,
      "ma200": 8.91,
      "ma50": 7.03,
      "peRatio": null,
      "forwardPE": -3.78,
      "priceToBook": -1.32,
      "week52High": 15.57,
      "week52Low": 5.6,
      "scores": {
        "dividendDaddy": 47,
        "moonShot": 39,
        "fallingKnife": 95,
        "overHyped": 2,
        "instWhale": 2
      }
    },
    {
      "symbol": "CTGO",
      "name": "Contango ORE, Inc. Common Stock",
      "exchange": "NYSE MKT",
      "sector": "Basic Materials",
      "industry": "Gold",
      "price": 18.55,
      "volume": 773705,
      "marketCap": 565915968,
      "dividendYield": null,
      "beta": -0.37,
      "rsi": 24.2,
      "ma200": 23.8,
      "ma50": 25.8,
      "peRatio": null,
      "forwardPE": 3.83,
      "priceToBook": 10.78,
      "week52High": 34.38,
      "week52Low": 9.22,
      "scores": {
        "dividendDaddy": 45,
        "moonShot": 11,
        "fallingKnife": 92,
        "overHyped": 2,
        "instWhale": 15
      }
    },
    {
      "symbol": "MMYT",
      "name": "MakeMyTrip Limited - Ordinary Shares",
      "exchange": "NASDAQ",
      "sector": "Consumer Cyclical",
      "industry": "Travel Services",
      "price": 37.88,
      "volume": 2428182,
      "marketCap": 3604183296,
      "dividendYield": null,
      "beta": 0.67,
      "rsi": 24.3,
      "ma200": 80.0,
      "ma50": 52.44,
      "peRatio": 72.85,
      "forwardPE": 17.55,
      "priceToBook": -318.32,
      "week52High": 113.85,
      "week52Low": 32.67,
      "scores": {
        "dividendDaddy": 40,
        "moonShot": 66,
        "fallingKnife": 99,
        "overHyped": 2,
        "instWhale": 52
      }
    },
    {
      "symbol": "UHS",
      "name": "Universal Health Services, Inc. Common Stock",
      "exchange": "NYSE",
      "sector": "Healthcare",
      "industry": "Medical Care Facilities",
      "price": 177.94,
      "volume": 601069,
      "marketCap": 10869756928,
      "dividendYield": 45.0,
      "beta": 1.26,
      "rsi": 24.5,
      "ma200": 200.27,
      "ma50": 204.01,
      "peRatio": 7.7,
      "forwardPE": 6.96,
      "priceToBook": 1.49,
      "week52High": 246.33,
      "week52Low": 152.33,
      "scores": {
        "dividendDaddy": 45,
        "moonShot": 89,
        "fallingKnife": 87,
        "overHyped": 2,
        "instWhale": 74
      }
    },
    {
      "symbol": "SUNS",
      "name": "Sunrise Realty Trust, Inc. - Common Stock",
      "exchange": "NASDAQ",
      "sector": "Real Estate",
      "industry": "REIT - Mortgage",
      "price": 7.76,
      "volume": 156709,
      "marketCap": 104912528,
      "dividendYield": 1564.0,
      "beta": null,
      "rsi": 24.6,
      "ma200": 9.24,
      "ma50": 8.67,
      "peRatio": 8.34,
      "forwardPE": 5.83,
      "priceToBook": 0.57,
      "week52High": 11.78,
      "week52Low": 7.46,
      "scores": {
        "dividendDaddy": 99,
        "moonShot": 26,
        "fallingKnife": 90,
        "overHyped": 2,
        "instWhale": 1
      }
    },
    {
      "symbol": "TMDX",
      "name": "TransMedics Group, Inc. - Common Stock",
      "exchange": "NASDAQ",
      "sector": "Healthcare",
      "industry": "Medical Devices",
      "price": 100.4,
      "volume": 790744,
      "marketCap": 3443966208,
      "dividendYield": null,
      "beta": 1.96,
      "rsi": 24.7,
      "ma200": 124.45,
      "ma50": 128.3,
      "peRatio": 20.62,
      "forwardPE": 27.08,
      "priceToBook": 7.27,
      "week52High": 156.0,
      "week52Low": 62.23,
      "scores": {
        "dividendDaddy": 6,
        "moonShot": 96,
        "fallingKnife": 91,
        "overHyped": 2,
        "instWhale": 51
      }
    },
    {
      "symbol": "ADUS",
      "name": "Addus HomeCare Corporation - Common Stock",
      "exchange": "NASDAQ",
      "sector": "Healthcare",
      "industry": "Medical Care Facilities",
      "price": 93.85,
      "volume": 242729,
      "marketCap": 1749703296,
      "dividendYield": null,
      "beta": 0.93,
      "rsi": 24.9,
      "ma200": 111.17,
      "ma50": 104.79,
      "peRatio": 17.98,
      "forwardPE": 12.61,
      "priceToBook": 1.57,
      "week52High": 124.44,
      "week52Low": 92.82,
      "scores": {
        "dividendDaddy": 34,
        "moonShot": 79,
        "fallingKnife": 89,
        "overHyped": 2,
        "instWhale": 36
      }
    },
    {
      "symbol": "BR",
      "name": "Broadridge Financial Solutions, Inc. Common Stock",
      "exchange": "NYSE",
      "sector": "Technology",
      "industry": "Information Technology Services",
      "price": 159.98,
      "volume": 2119547,
      "marketCap": 18677458944,
      "dividendYield": 240.0,
      "beta": 0.98,
      "rsi": 25.0,
      "ma200": 221.31,
      "ma50": 181.35,
      "peRatio": 17.72,
      "forwardPE": 15.46,
      "priceToBook": 6.48,
      "week52High": 271.91,
      "week52Low": 155.54,
      "scores": {
        "dividendDaddy": 69,
        "moonShot": 81,
        "fallingKnife": 94,
        "overHyped": 2,
        "instWhale": 81
      }
    },
    {
      "symbol": "MLKN",
      "name": "MillerKnoll, Inc. - Common Stock",
      "exchange": "NASDAQ",
      "sector": "Consumer Cyclical",
      "industry": "Furnishings, Fixtures & Appliances",
      "price": 14.5,
      "volume": 1370700,
      "marketCap": 991433664,
      "dividendYield": 518.0,
      "beta": 1.3,
      "rsi": 25.0,
      "ma200": 18.34,
      "ma50": 19.6,
      "peRatio": 96.67,
      "forwardPE": 7.26,
      "priceToBook": 0.74,
      "week52High": 23.18,
      "week52Low": 13.77,
      "scores": {
        "dividendDaddy": 86,
        "moonShot": 89,
        "fallingKnife": 92,
        "overHyped": 2,
        "instWhale": 25
      }
    },
    {
      "symbol": "WDFC",
      "name": "WD-40 Company - Common Stock",
      "exchange": "NASDAQ",
      "sector": "Basic Materials",
      "industry": "Specialty Chemicals",
      "price": 205.61,
      "volume": 235666,
      "marketCap": 2781458432,
      "dividendYield": 192.0,
      "beta": 0.17,
      "rsi": 25.0,
      "ma200": 211.98,
      "ma50": 228.67,
      "peRatio": 31.2,
      "forwardPE": 31.34,
      "priceToBook": 10.51,
      "week52High": 253.48,
      "week52Low": 175.38,
      "scores": {
        "dividendDaddy": 68,
        "moonShot": 34,
        "fallingKnife": 83,
        "overHyped": 3,
        "instWhale": 46
      }
    },
    {
      "symbol": "SOFI",
      "name": "SoFi Technologies, Inc.  - Common Stock",
      "exchange": "NASDAQ",
      "sector": "Financial Services",
      "industry": "Credit Services",
      "price": 15.63,
      "volume": 57026217,
      "marketCap": 19932375040,
      "dividendYield": null,
      "beta": 2.26,
      "rsi": 25.1,
      "ma200": 23.81,
      "ma50": 19.54,
      "peRatio": 40.08,
      "forwardPE": 19.51,
      "priceToBook": 1.89,
      "week52High": 32.73,
      "week52Low": 8.6,
      "scores": {
        "dividendDaddy": 4,
        "moonShot": 97,
        "fallingKnife": 96,
        "overHyped": 3,
        "instWhale": 82
      }
    },
    {
      "symbol": "PODD",
      "name": "Insulet Corporation - Common Stock",
      "exchange": "NASDAQ",
      "sector": "Healthcare",
      "industry": "Medical Devices",
      "price": 207.04,
      "volume": 1158006,
      "marketCap": 14574755840,
      "dividendYield": null,
      "beta": 1.44,
      "rsi": 25.1,
      "ma200": 293.39,
      "ma50": 241.94,
      "peRatio": 59.49,
      "forwardPE": 25.62,
      "priceToBook": 9.62,
      "week52High": 354.88,
      "week52Low": 203.19,
      "scores": {
        "dividendDaddy": 15,
        "moonShot": 91,
        "fallingKnife": 95,
        "overHyped": 3,
        "instWhale": 78
      }
    },
    {
      "symbol": "JOBY",
      "name": "Joby Aviation, Inc. Common Stock",
      "exchange": "NYSE",
      "sector": "Industrials",
      "industry": "Airports & Air Services",
      "price": 8.27,
      "volume": 18998610,
      "marketCap": 8099094528,
      "dividendYield": null,
      "beta": 2.66,
      "rsi": 25.4,
      "ma200": 13.7,
      "ma50": 10.24,
      "peRatio": null,
      "forwardPE": -17.78,
      "priceToBook": 5.37,
      "week52High": 20.95,
      "week52Low": 4.96,
      "scores": {
        "dividendDaddy": 2,
        "moonShot": 98,
        "fallingKnife": 97,
        "overHyped": 3,
        "instWhale": 69
      }
    },
    {
      "symbol": "HNI",
      "name": "HNI Corporation Common Stock",
      "exchange": "NYSE",
      "sector": "Consumer Cyclical",
      "industry": "Furnishings, Fixtures & Appliances",
      "price": 33.42,
      "volume": 567490,
      "marketCap": 2406002944,
      "dividendYield": 407.0,
      "beta": 0.9,
      "rsi": 25.5,
      "ma200": 44.14,
      "ma50": 43.81,
      "peRatio": 30.11,
      "forwardPE": 6.93,
      "priceToBook": 1.3,
      "week52High": 53.29,
      "week52Low": 32.59,
      "scores": {
        "dividendDaddy": 82,
        "moonShot": 78,
        "fallingKnife": 93,
        "overHyped": 3,
        "instWhale": 43
      }
    },
    {
      "symbol": "CPAY",
      "name": "Corpay, Inc. Common Stock",
      "exchange": "NYSE",
      "sector": "Technology",
      "industry": "Software - Infrastructure",
      "price": 289.58,
      "volume": 458594,
      "marketCap": 20258453504,
      "dividendYield": null,
      "beta": 0.82,
      "rsi": 25.7,
      "ma200": 310.3,
      "ma50": 319.38,
      "peRatio": 19.25,
      "forwardPE": 9.76,
      "priceToBook": 5.1,
      "week52High": 361.99,
      "week52Low": 252.84,
      "scores": {
        "dividendDaddy": 37,
        "moonShot": 74,
        "fallingKnife": 84,
        "overHyped": 3,
        "instWhale": 82
      }
    },
    {
      "symbol": "ALMU",
      "name": "Aeluma, Inc. - Common Stock",
      "exchange": "NASDAQ",
      "sector": "Technology",
      "industry": "Semiconductors",
      "price": 12.85,
      "volume": 328192,
      "marketCap": 231933584,
      "dividendYield": null,
      "beta": -1.75,
      "rsi": 25.8,
      "ma200": 16.88,
      "ma50": 15.44,
      "peRatio": null,
      "forwardPE": -58.41,
      "priceToBook": 5.67,
      "week52High": 25.88,
      "week52Low": 5.79,
      "scores": {
        "dividendDaddy": 9,
        "moonShot": null,
        "fallingKnife": 93,
        "overHyped": 3,
        "instWhale": 4
      }
    },
    {
      "symbol": "EGAN",
      "name": "eGain Corporation - Common Stock",
      "exchange": "NASDAQ",
      "sector": "Technology",
      "industry": "Software - Application",
      "price": 7.78,
      "volume": 164487,
      "marketCap": 213063936,
      "dividendYield": null,
      "beta": 0.88,
      "rsi": 26.1,
      "ma200": 9.35,
      "ma50": 9.36,
      "peRatio": 6.13,
      "forwardPE": 20.65,
      "priceToBook": 2.4,
      "week52High": 15.95,
      "week52Low": 4.34,
      "scores": {
        "dividendDaddy": 35,
        "moonShot": 76,
        "fallingKnife": 90,
        "overHyped": 3,
        "instWhale": 3
      }
    },
    {
      "symbol": "QBTS",
      "name": "D-Wave Quantum Inc. Common Shares",
      "exchange": "NYSE",
      "sector": "Technology",
      "industry": "Computer Hardware",
      "price": 13.7,
      "volume": 20044978,
      "marketCap": 5067817472,
      "dividendYield": null,
      "beta": 1.66,
      "rsi": 26.3,
      "ma200": 22.42,
      "ma50": 19.09,
      "peRatio": null,
      "forwardPE": -37.1,
      "priceToBook": 5.77,
      "week52High": 46.75,
      "week52Low": 5.77,
      "scores": {
        "dividendDaddy": 11,
        "moonShot": 94,
        "fallingKnife": 97,
        "overHyped": 3,
        "instWhale": 59
      }
    },
    {
      "symbol": "CSGP",
      "name": "CoStar Group, Inc. - Common Stock",
      "exchange": "NASDAQ",
      "sector": "Real Estate",
      "industry": "Real Estate Services",
      "price": 39.63,
      "volume": 5104778,
      "marketCap": 16796097536,
      "dividendYield": null,
      "beta": 0.9,
      "rsi": 26.5,
      "ma200": 71.05,
      "ma50": 49.14,
      "peRatio": 1981.5,
      "forwardPE": 22.32,
      "priceToBook": 1.99,
      "week52High": 97.43,
      "week52Low": 38.69,
      "scores": {
        "dividendDaddy": 35,
        "moonShot": 77,
        "fallingKnife": 98,
        "overHyped": 3,
        "instWhale": 80
      }
    },
    {
      "symbol": "AGL",
      "name": "agilon health, inc. Common Stock",
      "exchange": "NYSE",
      "sector": "Healthcare",
      "industry": "Medical Care Facilities",
      "price": 9.75,
      "volume": 505610,
      "marketCap": 161908448,
      "dividendYield": null,
      "beta": 0.11,
      "rsi": 26.5,
      "ma200": 26.03,
      "ma50": 14.53,
      "peRatio": null,
      "forwardPE": -1.99,
      "priceToBook": 1.28,
      "week52High": 152.0,
      "week52Low": 7.48,
      "scores": {
        "dividendDaddy": 48,
        "moonShot": 29,
        "fallingKnife": 99,
        "overHyped": 3,
        "instWhale": 2
      }
    },
    {
      "symbol": "AXON",
      "name": "Axon Enterprise, Inc. - Common Stock",
      "exchange": "NASDAQ",
      "sector": "Industrials",
      "industry": "Aerospace & Defense",
      "price": 423.57,
      "volume": 678524,
      "marketCap": 34054041600,
      "dividendYield": null,
      "beta": 1.52,
      "rsi": 26.6,
      "ma200": 641.6,
      "ma50": 493.59,
      "peRatio": 276.84,
      "forwardPE": 40.08,
      "priceToBook": 10.48,
      "week52High": 885.92,
      "week52Low": 396.41,
      "scores": {
        "dividendDaddy": 13,
        "moonShot": 92,
        "fallingKnife": 96,
        "overHyped": 3,
        "instWhale": 87
      }
    },
    {
      "symbol": "FIS",
      "name": "Fidelity National Information Services, Inc. Common Stock",
      "exchange": "NYSE",
      "sector": "Technology",
      "industry": "Information Technology Services",
      "price": 45.17,
      "volume": 6557555,
      "marketCap": 23391318016,
      "dividendYield": 350.0,
      "beta": 0.91,
      "rsi": 26.6,
      "ma200": 64.19,
      "ma50": 50.6,
      "peRatio": 61.88,
      "forwardPE": 6.55,
      "priceToBook": 1.67,
      "week52High": 82.74,
      "week52Low": 44.56,
      "scores": {
        "dividendDaddy": 78,
        "moonShot": 77,
        "fallingKnife": 95,
        "overHyped": 3,
        "instWhale": 84
      }
    },
    {
      "symbol": "HELE",
      "name": "Helen of Troy Limited - Common Stock",
      "exchange": "NASDAQ",
      "sector": "Consumer Defensive",
      "industry": "Household & Personal Products",
      "price": 14.49,
      "volume": 767980,
      "marketCap": 334314784,
      "dividendYield": null,
      "beta": 0.8,
      "rsi": 26.6,
      "ma200": 21.05,
      "ma50": 16.85,
      "peRatio": null,
      "forwardPE": 4.32,
      "priceToBook": 0.39,
      "week52High": 53.37,
      "week52Low": 13.85,
      "scores": {
        "dividendDaddy": 37,
        "moonShot": 72,
        "fallingKnife": 95,
        "overHyped": 3,
        "instWhale": 7
      }
    },
    {
      "symbol": "MSFT",
      "name": "Microsoft Corporation - Common Stock",
      "exchange": "NASDAQ",
      "sector": "Technology",
      "industry": "Software - Infrastructure",
      "price": 369.37,
      "volume": 28264760,
      "marketCap": 2745297272832,
      "dividendYield": 98.0,
      "beta": 1.11,
      "rsi": 26.9,
      "ma200": 475.78,
      "ma50": 404.63,
      "peRatio": 23.1,
      "forwardPE": 19.59,
      "priceToBook": 7.02,
      "week52High": 555.45,
      "week52Low": 344.79,
      "scores": {
        "dividendDaddy": 54,
        "moonShot": 84,
        "fallingKnife": 92,
        "overHyped": 3,
        "instWhale": 99
      }
    },
    {
      "symbol": "CLPT",
      "name": "ClearPoint Neuro Inc. - Common Stock",
      "exchange": "NASDAQ",
      "sector": "Healthcare",
      "industry": "Medical Devices",
      "price": 9.14,
      "volume": 440852,
      "marketCap": 271899552,
      "dividendYield": null,
      "beta": 1.07,
      "rsi": 27.0,
      "ma200": 14.18,
      "ma50": 12.03,
      "peRatio": null,
      "forwardPE": -11.21,
      "priceToBook": 9.58,
      "week52High": 30.1,
      "week52Low": 8.6,
      "scores": {
        "dividendDaddy": 24,
        "moonShot": 83,
        "fallingKnife": 96,
        "overHyped": 3,
        "instWhale": 5
      }
    },
    {
      "symbol": "DMRC",
      "name": "Digimarc Corporation - Common Stock",
      "exchange": "NASDAQ",
      "sector": "Technology",
      "industry": "Software - Application",
      "price": 5.06,
      "volume": 237349,
      "marketCap": 111792040,
      "dividendYield": null,
      "beta": 1.76,
      "rsi": 27.0,
      "ma200": 8.53,
      "ma50": 5.31,
      "peRatio": null,
      "forwardPE": -59.53,
      "priceToBook": 2.75,
      "week52High": 14.64,
      "week52Low": 4.07,
      "scores": {
        "dividendDaddy": 9,
        "moonShot": 95,
        "fallingKnife": 97,
        "overHyped": 3,
        "instWhale": 1
      }
    },
    {
      "symbol": "MAGN",
      "name": "Magnera Corporation Common Stock",
      "exchange": "NYSE",
      "sector": "Consumer Defensive",
      "industry": "Household & Personal Products",
      "price": 9.48,
      "volume": 449649,
      "marketCap": 337487968,
      "dividendYield": null,
      "beta": null,
      "rsi": 27.1,
      "ma200": 12.26,
      "ma50": 12.29,
      "peRatio": null,
      "forwardPE": 10.09,
      "priceToBook": 0.33,
      "week52High": 18.61,
      "week52Low": 7.82,
      "scores": {
        "dividendDaddy": 29,
        "moonShot": 23,
        "fallingKnife": 92,
        "overHyped": 3,
        "instWhale": 8
      }
    },
    {
      "symbol": "COR",
      "name": "Cencora, Inc. Common Stock",
      "exchange": "NYSE",
      "sector": "Healthcare",
      "industry": "Medical Distribution",
      "price": 317.66,
      "volume": 1208512,
      "marketCap": 61794619392,
      "dividendYield": 76.0,
      "beta": 0.65,
      "rsi": 27.2,
      "ma200": 325.24,
      "ma50": 349.35,
      "peRatio": 38.18,
      "forwardPE": 16.18,
      "priceToBook": 32.38,
      "week52High": 377.54,
      "week52Low": 267.4,
      "scores": {
        "dividendDaddy": 54,
        "moonShot": 62,
        "fallingKnife": 80,
        "overHyped": 3,
        "instWhale": 92
      }
    },
    {
      "symbol": "PD",
      "name": "PagerDuty, Inc. Common Stock",
      "exchange": "NYSE",
      "sector": "Technology",
      "industry": "Software - Application",
      "price": 6.32,
      "volume": 1724941,
      "marketCap": 580029440,
      "dividendYield": null,
      "beta": 0.75,
      "rsi": 27.3,
      "ma200": 13.15,
      "ma50": 7.78,
      "peRatio": 3.38,
      "forwardPE": 4.58,
      "priceToBook": 2.11,
      "week52High": 18.51,
      "week52Low": 5.92,
      "scores": {
        "dividendDaddy": 38,
        "moonShot": 68,
        "fallingKnife": 99,
        "overHyped": 3,
        "instWhale": 15
      }
    },
    {
      "symbol": "GEN",
      "name": "Gen Digital Inc. - Common Stock",
      "exchange": "NASDAQ",
      "sector": "Technology",
      "industry": "Software - Infrastructure",
      "price": 18.71,
      "volume": 7936967,
      "marketCap": 11538757632,
      "dividendYield": 266.0,
      "beta": 1.09,
      "rsi": 27.3,
      "ma200": 26.58,
      "ma50": 22.27,
      "peRatio": 19.29,
      "forwardPE": 6.52,
      "priceToBook": 4.86,
      "week52High": 32.22,
      "week52Low": 18.21,
      "scores": {
        "dividendDaddy": 70,
        "moonShot": 83,
        "fallingKnife": 94,
        "overHyped": 3,
        "instWhale": 75
      }
    },
    {
      "symbol": "OLLI",
      "name": "Ollie's Bargain Outlet Holdings, Inc. - Common Stock",
      "exchange": "NASDAQ",
      "sector": "Consumer Defensive",
      "industry": "Discount Stores",
      "price": 91.24,
      "volume": 1302866,
      "marketCap": 5595981824,
      "dividendYield": null,
      "beta": 0.53,
      "rsi": 27.3,
      "ma200": 120.79,
      "ma50": 105.78,
      "peRatio": 23.46,
      "forwardPE": 17.87,
      "priceToBook": 2.95,
      "week52High": 141.74,
      "week52Low": 88.44,
      "scores": {
        "dividendDaddy": 43,
        "moonShot": 54,
        "fallingKnife": 92,
        "overHyped": 3,
        "instWhale": 62
      }
    },
    {
      "symbol": "PM",
      "name": "Philip Morris International Inc Common Stock",
      "exchange": "NYSE",
      "sector": "Consumer Defensive",
      "industry": "Tobacco",
      "price": 157.33,
      "volume": 10054975,
      "marketCap": 245203582976,
      "dividendYield": 356.0,
      "beta": 0.4,
      "rsi": 27.4,
      "ma200": 163.31,
      "ma50": 174.53,
      "peRatio": 21.67,
      "forwardPE": 17.1,
      "priceToBook": -24.51,
      "week52High": 191.3,
      "week52Low": 142.11,
      "scores": {
        "dividendDaddy": 80,
        "moonShot": 45,
        "fallingKnife": 81,
        "overHyped": 4,
        "instWhale": 98
      }
    },
    {
      "symbol": "ALRM",
      "name": "Alarm.com Holdings, Inc. - Common Stock",
      "exchange": "NASDAQ",
      "sector": "Technology",
      "industry": "Software - Application",
      "price": 43.3,
      "volume": 309633,
      "marketCap": 2159790080,
      "dividendYield": null,
      "beta": 0.81,
      "rsi": 27.5,
      "ma200": 51.79,
      "ma50": 46.8,
      "peRatio": 17.6,
      "forwardPE": 14.57,
      "priceToBook": 2.53,
      "week52High": 60.76,
      "week52Low": 41.5,
      "scores": {
        "dividendDaddy": 37,
        "moonShot": 71,
        "fallingKnife": 89,
        "overHyped": 4,
        "instWhale": 41
      }
    },
    {
      "symbol": "NSIT",
      "name": "Insight Enterprises, Inc. - Common Stock",
      "exchange": "NASDAQ",
      "sector": "Technology",
      "industry": "Electronics & Computer Distribution",
      "price": 67.23,
      "volume": 279979,
      "marketCap": 2083894912,
      "dividendYield": null,
      "beta": 0.89,
      "rsi": 27.6,
      "ma200": 103.63,
      "ma50": 80.69,
      "peRatio": 13.83,
      "forwardPE": 5.83,
      "priceToBook": 1.26,
      "week52High": 149.26,
      "week52Low": 63.62,
      "scores": {
        "dividendDaddy": 35,
        "moonShot": 75,
        "fallingKnife": 96,
        "overHyped": 4,
        "instWhale": 40
      }
    },
    {
      "symbol": "SNOW",
      "name": "Snowflake Inc. Common Stock",
      "exchange": "NYSE",
      "sector": "Technology",
      "industry": "Software - Application",
      "price": 153.12,
      "volume": 4462971,
      "marketCap": 52933582848,
      "dividendYield": null,
      "beta": 1.21,
      "rsi": 27.6,
      "ma200": 214.89,
      "ma50": 176.62,
      "peRatio": null,
      "forwardPE": 63.06,
      "priceToBook": 27.37,
      "week52High": 280.67,
      "week52Low": 120.1,
      "scores": {
        "dividendDaddy": 20,
        "moonShot": 87,
        "fallingKnife": 94,
        "overHyped": 4,
        "instWhale": 91
      }
    },
    {
      "symbol": "EPR",
      "name": "EPR Properties Common Stock",
      "exchange": "NYSE",
      "sector": "Real Estate",
      "industry": "REIT - Specialty",
      "price": 50.3,
      "volume": 938868,
      "marketCap": 3848956672,
      "dividendYield": 712.0,
      "beta": 0.96,
      "rsi": 27.6,
      "ma200": 52.96,
      "ma50": 54.83,
      "peRatio": 15.34,
      "forwardPE": 16.24,
      "priceToBook": 1.64,
      "week52High": 62.08,
      "week52Low": 41.75,
      "scores": {
        "dividendDaddy": 90,
        "moonShot": 78,
        "fallingKnife": 82,
        "overHyped": 4,
        "instWhale": 54
      }
    },
    {
      "symbol": "ORIC",
      "name": "Oric Pharmaceuticals, Inc. - Common Stock",
      "exchange": "NASDAQ",
      "sector": "Healthcare",
      "industry": "Biotechnology",
      "price": 7.47,
      "volume": 15468931,
      "marketCap": 837255168,
      "dividendYield": null,
      "beta": 1.36,
      "rsi": 27.6,
      "ma200": 11.04,
      "ma50": 11.67,
      "peRatio": null,
      "forwardPE": -4.83,
      "priceToBook": 1.92,
      "week52High": 14.93,
      "week52Low": 3.9,
      "scores": {
        "dividendDaddy": 16,
        "moonShot": 89,
        "fallingKnife": 95,
        "overHyped": 4,
        "instWhale": 22
      }
    },
    {
      "symbol": "TTD",
      "name": "The Trade Desk, Inc. - Class A Common Stock",
      "exchange": "NASDAQ",
      "sector": "Communication Services",
      "industry": "Advertising Agencies",
      "price": 21.98,
      "volume": 16606492,
      "marketCap": 10461975552,
      "dividendYield": null,
      "beta": 1.19,
      "rsi": 27.7,
      "ma200": 46.88,
      "ma50": 26.71,
      "peRatio": 24.42,
      "forwardPE": 9.22,
      "priceToBook": 4.21,
      "week52High": 91.45,
      "week52Low": 21.03,
      "scores": {
        "dividendDaddy": 21,
        "moonShot": 86,
        "fallingKnife": 99,
        "overHyped": 4,
        "instWhale": 73
      }
    },
    {
      "symbol": "RXST",
      "name": "RxSight, Inc. - Common Stock",
      "exchange": "NASDAQ",
      "sector": "Healthcare",
      "industry": "Medical Devices",
      "price": 6.34,
      "volume": 772015,
      "marketCap": 261628576,
      "dividendYield": null,
      "beta": 1.15,
      "rsi": 27.7,
      "ma200": 9.26,
      "ma50": 7.9,
      "peRatio": null,
      "forwardPE": -13.14,
      "priceToBook": 0.95,
      "week52High": 26.38,
      "week52Low": 5.9,
      "scores": {
        "dividendDaddy": 22,
        "moonShot": 85,
        "fallingKnife": 95,
        "overHyped": 4,
        "instWhale": 5
      }
    },
    {
      "symbol": "LE",
      "name": "Lands' End, Inc. - Common Stock",
      "exchange": "NASDAQ",
      "sector": "Consumer Cyclical",
      "industry": "Apparel Retail",
      "price": 11.56,
      "volume": 829604,
      "marketCap": 355988736,
      "dividendYield": null,
      "beta": 2.42,
      "rsi": 27.8,
      "ma200": 14.58,
      "ma50": 15.91,
      "peRatio": 64.22,
      "forwardPE": 9.92,
      "priceToBook": 1.45,
      "week52High": 20.04,
      "week52Low": 7.65,
      "scores": {
        "dividendDaddy": 3,
        "moonShot": 98,
        "fallingKnife": 91,
        "overHyped": 4,
        "instWhale": 8
      }
    },
    {
      "symbol": "SRAD",
      "name": "Sportradar Group AG - Class A Ordinary Shares",
      "exchange": "NASDAQ",
      "sector": "Technology",
      "industry": "Software - Application",
      "price": 16.63,
      "volume": 1689996,
      "marketCap": 4921675776,
      "dividendYield": null,
      "beta": 2.0,
      "rsi": 28.0,
      "ma200": 24.25,
      "ma50": 18.04,
      "peRatio": 46.19,
      "forwardPE": 20.25,
      "priceToBook": 4.41,
      "week52High": 32.22,
      "week52Low": 15.72,
      "scores": {
        "dividendDaddy": 6,
        "moonShot": 96,
        "fallingKnife": 95,
        "overHyped": 4,
        "instWhale": 59
      }
    },
    {
      "symbol": "RYAN",
      "name": "Ryan Specialty Holdings, Inc. Class A Common Stock",
      "exchange": "NYSE",
      "sector": "Financial Services",
      "industry": "Insurance - Specialty",
      "price": 33.03,
      "volume": 2549725,
      "marketCap": 8726184960,
      "dividendYield": 154.0,
      "beta": 0.65,
      "rsi": 28.1,
      "ma200": 52.81,
      "ma50": 40.4,
      "peRatio": 70.28,
      "forwardPE": 12.49,
      "priceToBook": 6.61,
      "week52High": 77.16,
      "week52Low": 31.5,
      "scores": {
        "dividendDaddy": 63,
        "moonShot": 61,
        "fallingKnife": 96,
        "overHyped": 4,
        "instWhale": 70
      }
    },
    {
      "symbol": "HDB",
      "name": "HDFC Bank Limited Common Stock",
      "exchange": "NYSE",
      "sector": "Financial Services",
      "industry": "Banks - Regional",
      "price": 24.9,
      "volume": 10117163,
      "marketCap": 127764381696,
      "dividendYield": 151.0,
      "beta": 0.36,
      "rsi": 28.2,
      "ma200": 34.71,
      "ma50": 30.4,
      "peRatio": 17.54,
      "forwardPE": 18.29,
      "priceToBook": 6.34,
      "week52High": 39.8,
      "week52Low": 23.91,
      "scores": {
        "dividendDaddy": 63,
        "moonShot": 42,
        "fallingKnife": 94,
        "overHyped": 4,
        "instWhale": 96
      }
    },
    {
      "symbol": "ULTA",
      "name": "Ulta Beauty, Inc. - Common Stock",
      "exchange": "NASDAQ",
      "sector": "Consumer Cyclical",
      "industry": "Specialty Retail",
      "price": 536.61,
      "volume": 682440,
      "marketCap": 23805184000,
      "dividendYield": null,
      "beta": 0.85,
      "rsi": 28.3,
      "ma200": 559.9,
      "ma50": 629.23,
      "peRatio": 20.9,
      "forwardPE": 17.02,
      "priceToBook": 8.45,
      "week52High": 714.97,
      "week52Low": 323.37,
      "scores": {
        "dividendDaddy": 36,
        "moonShot": 72,
        "fallingKnife": 81,
        "overHyped": 4,
        "instWhale": 84
      }
    },
    {
      "symbol": "ALKT",
      "name": "Alkami Technology, Inc. - Common Stock",
      "exchange": "NASDAQ",
      "sector": "Technology",
      "industry": "Software - Application",
      "price": 16.01,
      "volume": 1488251,
      "marketCap": 1699431808,
      "dividendYield": null,
      "beta": 0.56,
      "rsi": 28.3,
      "ma200": 22.38,
      "ma50": 17.53,
      "peRatio": null,
      "forwardPE": 14.51,
      "priceToBook": 4.69,
      "week52High": 31.66,
      "week52Low": 14.11,
      "scores": {
        "dividendDaddy": 42,
        "moonShot": 55,
        "fallingKnife": 94,
        "overHyped": 4,
        "instWhale": 36
      }
    },
    {
      "symbol": "VERX",
      "name": "Vertex, Inc. - Class A Common Stock",
      "exchange": "NASDAQ",
      "sector": "Technology",
      "industry": "Software - Application",
      "price": 12.09,
      "volume": 1086114,
      "marketCap": 1933878912,
      "dividendYield": null,
      "beta": 0.72,
      "rsi": 28.3,
      "ma200": 22.76,
      "ma50": 14.54,
      "peRatio": 302.25,
      "forwardPE": 13.74,
      "priceToBook": 7.44,
      "week52High": 42.44,
      "week52Low": 11.25,
      "scores": {
        "dividendDaddy": 39,
        "moonShot": 65,
        "fallingKnife": 98,
        "overHyped": 4,
        "instWhale": 38
      }
    },
    {
      "symbol": "PHR",
      "name": "Phreesia, Inc. Common Stock",
      "exchange": "NYSE",
      "sector": "Healthcare",
      "industry": "Health Information Services",
      "price": 8.4,
      "volume": 3929941,
      "marketCap": 509586112,
      "dividendYield": null,
      "beta": 0.72,
      "rsi": 28.4,
      "ma200": 20.74,
      "ma50": 12.29,
      "peRatio": 210.0,
      "forwardPE": 4.97,
      "priceToBook": 1.51,
      "week52High": 32.76,
      "week52Low": 7.77,
      "scores": {
        "dividendDaddy": 39,
        "moonShot": 64,
        "fallingKnife": 99,
        "overHyped": 4,
        "instWhale": 13
      }
    },
    {
      "symbol": "EXPO",
      "name": "Exponent, Inc. - Common Stock",
      "exchange": "NASDAQ",
      "sector": "Industrials",
      "industry": "Engineering & Construction",
      "price": 65.03,
      "volume": 385996,
      "marketCap": 3244166144,
      "dividendYield": 185.0,
      "beta": 0.78,
      "rsi": 28.5,
      "ma200": 70.56,
      "ma50": 70.17,
      "peRatio": 31.42,
      "forwardPE": 23.91,
      "priceToBook": 8.27,
      "week52High": 83.92,
      "week52Low": 63.25,
      "scores": {
        "dividendDaddy": 65,
        "moonShot": 68,
        "fallingKnife": 83,
        "overHyped": 4,
        "instWhale": 50
      }
    },
    {
      "symbol": "BSY",
      "name": "Bentley Systems, Incorporated - Class B Common Stock",
      "exchange": "NASDAQ",
      "sector": "Technology",
      "industry": "Software - Application",
      "price": 34.2,
      "volume": 1814033,
      "marketCap": 10381651968,
      "dividendYield": 80.0,
      "beta": 1.18,
      "rsi": 28.5,
      "ma200": 45.93,
      "ma50": 36.05,
      "peRatio": 40.24,
      "forwardPE": 21.72,
      "priceToBook": 9.0,
      "week52High": 59.25,
      "week52Low": 30.96,
      "scores": {
        "dividendDaddy": 51,
        "moonShot": 85,
        "fallingKnife": 93,
        "overHyped": 4,
        "instWhale": 73
      }
    },
    {
      "symbol": "IPX",
      "name": "IperionX Limited - American Depositary Share",
      "exchange": "NASDAQ",
      "sector": "Basic Materials",
      "industry": "Other Industrial Metals & Mining",
      "price": 27.66,
      "volume": 384220,
      "marketCap": 1009692096,
      "dividendYield": null,
      "beta": 0.87,
      "rsi": 28.5,
      "ma200": 40.5,
      "ma50": 41.56,
      "peRatio": null,
      "forwardPE": -99.32,
      "priceToBook": 85.9,
      "week52High": 61.45,
      "week52Low": 12.28,
      "scores": {
        "dividendDaddy": 36,
        "moonShot": 73,
        "fallingKnife": 95,
        "overHyped": 4,
        "instWhale": 25
      }
    },
    {
      "symbol": "SAP",
      "name": "SAP  SE ADS",
      "exchange": "NYSE",
      "sector": "Technology",
      "industry": "Software - Application",
      "price": 171.36,
      "volume": 2212102,
      "marketCap": 201503588352,
      "dividendYield": 173.0,
      "beta": 0.69,
      "rsi": 28.5,
      "ma200": 250.07,
      "ma50": 197.66,
      "peRatio": 24.48,
      "forwardPE": 17.17,
      "priceToBook": 3.88,
      "week52High": 313.28,
      "week52Low": 163.77,
      "scores": {
        "dividendDaddy": 64,
        "moonShot": 63,
        "fallingKnife": 95,
        "overHyped": 5,
        "instWhale": 98
      }
    },
    {
      "symbol": "NKX",
      "name": "Nuveen California AMT-Free Quality Municipal Income Fund",
      "exchange": "NYSE",
      "sector": "Financial Services",
      "industry": "Asset Management",
      "price": 11.98,
      "volume": 232451,
      "marketCap": 629044544,
      "dividendYield": 766.0,
      "beta": 0.6,
      "rsi": 28.5,
      "ma200": 12.06,
      "ma50": 12.61,
      "peRatio": null,
      "forwardPE": null,
      "priceToBook": 1.04,
      "week52High": 13.2,
      "week52Low": 11.44,
      "scores": {
        "dividendDaddy": 92,
        "moonShot": 57,
        "fallingKnife": 78,
        "overHyped": 5,
        "instWhale": 17
      }
    },
    {
      "symbol": "ADBE",
      "name": "Adobe Inc. - Common Stock",
      "exchange": "NASDAQ",
      "sector": "Technology",
      "industry": "Software - Application",
      "price": 241.37,
      "volume": 3741601,
      "marketCap": 98391326720,
      "dividendYield": null,
      "beta": 1.53,
      "rsi": 28.6,
      "ma200": 328.56,
      "ma50": 265.88,
      "peRatio": 14.07,
      "forwardPE": 9.16,
      "priceToBook": 8.57,
      "week52High": 422.95,
      "week52Low": 233.16,
      "scores": {
        "dividendDaddy": 13,
        "moonShot": 92,
        "fallingKnife": 93,
        "overHyped": 5,
        "instWhale": 95
      }
    },
    {
      "symbol": "TSQ",
      "name": "Townsquare Media, Inc. Class A Common Stock",
      "exchange": "NYSE",
      "sector": "Communication Services",
      "industry": "Advertising Agencies",
      "price": 5.43,
      "volume": 131758,
      "marketCap": 92880768,
      "dividendYield": 1473.0,
      "beta": 0.97,
      "rsi": 28.6,
      "ma200": 6.16,
      "ma50": 6.48,
      "peRatio": null,
      "forwardPE": 13.24,
      "priceToBook": -2.02,
      "week52High": 9.31,
      "week52Low": 4.3,
      "scores": {
        "dividendDaddy": 98,
        "moonShot": 78,
        "fallingKnife": 86,
        "overHyped": 5,
        "instWhale": 1
      }
    },
    {
      "symbol": "CMCSA",
      "name": "Comcast Corporation - Class A Common Stock",
      "exchange": "NASDAQ",
      "sector": "Communication Services",
      "industry": "Telecom Services",
      "price": 28.05,
      "volume": 25783016,
      "marketCap": 102211239936,
      "dividendYield": 460.0,
      "beta": 0.78,
      "rsi": 28.6,
      "ma200": 29.12,
      "ma50": 30.27,
      "peRatio": 5.2,
      "forwardPE": 7.24,
      "priceToBook": 1.04,
      "week52High": 34.36,
      "week52Low": 24.13,
      "scores": {
        "dividendDaddy": 85,
        "moonShot": 68,
        "fallingKnife": 80,
        "overHyped": 5,
        "instWhale": 95
      }
    },
    {
      "symbol": "CHE",
      "name": "Chemed Corp",
      "exchange": "NYSE",
      "sector": "Healthcare",
      "industry": "Medical Care Facilities",
      "price": 377.57,
      "volume": 139438,
      "marketCap": 5327102976,
      "dividendYield": 61.0,
      "beta": 0.46,
      "rsi": 28.6,
      "ma200": 443.1,
      "ma50": 422.97,
      "peRatio": 20.56,
      "forwardPE": 14.18,
      "priceToBook": 5.29,
      "week52High": 623.61,
      "week52Low": 365.21,
      "scores": {
        "dividendDaddy": 54,
        "moonShot": 48,
        "fallingKnife": 88,
        "overHyped": 5,
        "instWhale": 60
      }
    },
    {
      "symbol": "NMAX",
      "name": "Newsmax, Inc. Class B Common Stock",
      "exchange": "NYSE",
      "sector": "Communication Services",
      "industry": "Broadcasting",
      "price": 5.5,
      "volume": 1094507,
      "marketCap": 710261504,
      "dividendYield": null,
      "beta": null,
      "rsi": 28.6,
      "ma200": 10.14,
      "ma50": 6.48,
      "peRatio": null,
      "forwardPE": 550.0,
      "priceToBook": 6.7,
      "week52High": 177.01,
      "week52Low": 5.11,
      "scores": {
        "dividendDaddy": 29,
        "moonShot": 21,
        "fallingKnife": 98,
        "overHyped": 5,
        "instWhale": 19
      }
    },
    {
      "symbol": "TPB",
      "name": "Turning Point Brands, Inc. Common Stock",
      "exchange": "NYSE",
      "sector": "Consumer Defensive",
      "industry": "Tobacco",
      "price": 74.25,
      "volume": 2192397,
      "marketCap": 1436048640,
      "dividendYield": 35.0,
      "beta": 0.85,
      "rsi": 28.7,
      "ma200": 98.22,
      "ma50": 110.79,
      "peRatio": 23.87,
      "forwardPE": 16.96,
      "priceToBook": 4.01,
      "week52High": 146.9,
      "week52Low": 51.48,
      "scores": {
        "dividendDaddy": 48,
        "moonShot": 72,
        "fallingKnife": 92,
        "overHyped": 5,
        "instWhale": 32
      }
    },
    {
      "symbol": "HNGE",
      "name": "Hinge Health, Inc. Class A Common Stock",
      "exchange": "NYSE",
      "sector": "Healthcare",
      "industry": "Health Information Services",
      "price": 38.49,
      "volume": 382767,
      "marketCap": 3031597312,
      "dividendYield": null,
      "beta": null,
      "rsi": 28.7,
      "ma200": 47.19,
      "ma50": 40.36,
      "peRatio": null,
      "forwardPE": 16.71,
      "priceToBook": 17.05,
      "week52High": 62.18,
      "week52Low": 30.08,
      "scores": {
        "dividendDaddy": 29,
        "moonShot": 21,
        "fallingKnife": 89,
        "overHyped": 5,
        "instWhale": 48
      }
    },
    {
      "symbol": "BKKT",
      "name": "Bakkt Holdings, Inc. Class A Common Stock",
      "exchange": "NYSE",
      "sector": "Technology",
      "industry": "Software - Infrastructure",
      "price": 7.24,
      "volume": 674133,
      "marketCap": 221269568,
      "dividendYield": null,
      "beta": 6.1,
      "rsi": 28.7,
      "ma200": 15.78,
      "ma50": 10.49,
      "peRatio": null,
      "forwardPE": 7.54,
      "priceToBook": 1.64,
      "week52High": 49.79,
      "week52Low": 6.81,
      "scores": {
        "dividendDaddy": null,
        "moonShot": 99,
        "fallingKnife": 99,
        "overHyped": 5,
        "instWhale": 4
      }
    },
    {
      "symbol": "MZTI",
      "name": "The Marzetti Company - Common Stock",
      "exchange": "NASDAQ",
      "sector": "Consumer Defensive",
      "industry": "Packaged Foods",
      "price": 138.48,
      "volume": 223572,
      "marketCap": 3806261248,
      "dividendYield": 289.0,
      "beta": 0.41,
      "rsi": 28.9,
      "ma200": 166.74,
      "ma50": 156.22,
      "peRatio": 21.17,
      "forwardPE": 18.81,
      "priceToBook": 3.68,
      "week52High": 193.4,
      "week52Low": 136.72,
      "scores": {
        "dividendDaddy": 76,
        "moonShot": 45,
        "fallingKnife": 89,
        "overHyped": 5,
        "instWhale": 53
      }
    },
    {
      "symbol": "FBIN",
      "name": "Fortune Brands Innovations, Inc. Common Stock",
      "exchange": "NYSE",
      "sector": "Industrials",
      "industry": "Building Products & Equipment",
      "price": 38.28,
      "volume": 1139576,
      "marketCap": 4598896128,
      "dividendYield": 267.0,
      "beta": 1.47,
      "rsi": 29.1,
      "ma200": 52.27,
      "ma50": 50.48,
      "peRatio": 15.5,
      "forwardPE": 9.63,
      "priceToBook": 1.92,
      "week52High": 64.84,
      "week52Low": 37.07,
      "scores": {
        "dividendDaddy": 69,
        "moonShot": 91,
        "fallingKnife": 93,
        "overHyped": 5,
        "instWhale": 57
      }
    },
    {
      "symbol": "SCVL",
      "name": "Shoe Carnival, Inc. - Common Stock",
      "exchange": "NASDAQ",
      "sector": "Consumer Cyclical",
      "industry": "Apparel Retail",
      "price": 15.88,
      "volume": 501918,
      "marketCap": 436216800,
      "dividendYield": 398.0,
      "beta": 1.27,
      "rsi": 29.2,
      "ma200": 19.46,
      "ma50": 19.01,
      "peRatio": 8.36,
      "forwardPE": 8.61,
      "priceToBook": 0.63,
      "week52High": 26.57,
      "week52Low": 15.04,
      "scores": {
        "dividendDaddy": 80,
        "moonShot": 87,
        "fallingKnife": 89,
        "overHyped": 5,
        "instWhale": 11
      }
    },
    {
      "symbol": "MP",
      "name": "MP Materials Corp. Common Stock",
      "exchange": "NYSE",
      "sector": "Basic Materials",
      "industry": "Other Industrial Metals & Mining",
      "price": 48.41,
      "volume": 4881004,
      "marketCap": 8600881152,
      "dividendYield": null,
      "beta": 1.62,
      "rsi": 29.3,
      "ma200": 60.68,
      "ma50": 58.7,
      "peRatio": null,
      "forwardPE": 37.79,
      "priceToBook": 4.34,
      "week52High": 100.25,
      "week52Low": 18.64,
      "scores": {
        "dividendDaddy": 11,
        "moonShot": 93,
        "fallingKnife": 90,
        "overHyped": 5,
        "instWhale": 70
      }
    },
    {
      "symbol": "GIS",
      "name": "General Mills, Inc. Common Stock",
      "exchange": "NYSE",
      "sector": "Consumer Defensive",
      "industry": "Packaged Foods",
      "price": 37.21,
      "volume": 7557146,
      "marketCap": 19858278400,
      "dividendYield": 656.0,
      "beta": -0.1,
      "rsi": 29.3,
      "ma200": 46.51,
      "ma50": 43.05,
      "peRatio": 9.1,
      "forwardPE": 11.3,
      "priceToBook": 2.13,
      "week52High": 62.61,
      "week52Low": 35.64,
      "scores": {
        "dividendDaddy": 90,
        "moonShot": 17,
        "fallingKnife": 90,
        "overHyped": 5,
        "instWhale": 82
      }
    },
    {
      "symbol": "MEG",
      "name": "Montrose Environmental Group, Inc. Common Stock",
      "exchange": "NYSE",
      "sector": "Industrials",
      "industry": "Waste Management",
      "price": 22.37,
      "volume": 271341,
      "marketCap": 809118016,
      "dividendYield": null,
      "beta": 1.93,
      "rsi": 29.4,
      "ma200": 25.36,
      "ma50": 23.83,
      "peRatio": null,
      "forwardPE": 13.52,
      "priceToBook": 1.78,
      "week52High": 32.0,
      "week52Low": 10.51,
      "scores": {
        "dividendDaddy": 6,
        "moonShot": 96,
        "fallingKnife": 85,
        "overHyped": 5,
        "instWhale": 22
      }
    },
    {
      "symbol": "FLNC",
      "name": "Fluence Energy, Inc. - Class A Common Stock",
      "exchange": "NASDAQ",
      "sector": "Utilities",
      "industry": "Utilities - Renewable",
      "price": 13.02,
      "volume": 4278304,
      "marketCap": 2394837504,
      "dividendYield": null,
      "beta": 2.99,
      "rsi": 29.4,
      "ma200": 15.18,
      "ma50": 19.14,
      "peRatio": null,
      "forwardPE": 59.97,
      "priceToBook": 4.44,
      "week52High": 33.51,
      "week52Low": 3.46,
      "scores": {
        "dividendDaddy": 1,
        "moonShot": 98,
        "fallingKnife": 87,
        "overHyped": 5,
        "instWhale": 43
      }
    },
    {
      "symbol": "KTOS",
      "name": "Kratos Defense & Security Solutions, Inc. - Common Stock",
      "exchange": "NASDAQ",
      "sector": "Industrials",
      "industry": "Aerospace & Defense",
      "price": 67.7,
      "volume": 4277283,
      "marketCap": 12643497984,
      "dividendYield": null,
      "beta": 1.15,
      "rsi": 29.4,
      "ma200": 78.43,
      "ma50": 92.07,
      "peRatio": 520.77,
      "forwardPE": 63.2,
      "priceToBook": 5.73,
      "week52High": 134.0,
      "week52Low": 25.78,
      "scores": {
        "dividendDaddy": 22,
        "moonShot": 84,
        "fallingKnife": 86,
        "overHyped": 5,
        "instWhale": 76
      }
    },
    {
      "symbol": "DKNG",
      "name": "DraftKings Inc. - Class A Common Stock",
      "exchange": "NASDAQ",
      "sector": "Consumer Cyclical",
      "industry": "Gambling",
      "price": 22.16,
      "volume": 13279036,
      "marketCap": 10985660416,
      "dividendYield": null,
      "beta": 1.68,
      "rsi": 29.4,
      "ma200": 35.14,
      "ma50": 25.17,
      "peRatio": null,
      "forwardPE": 11.96,
      "priceToBook": 17.37,
      "week52High": 48.78,
      "week52Low": 20.46,
      "scores": {
        "dividendDaddy": 10,
        "moonShot": 93,
        "fallingKnife": 96,
        "overHyped": 5,
        "instWhale": 74
      }
    },
    {
      "symbol": "FTDR",
      "name": "Frontdoor, Inc. - Common Stock",
      "exchange": "NASDAQ",
      "sector": "Consumer Cyclical",
      "industry": "Personal Services",
      "price": 54.52,
      "volume": 657563,
      "marketCap": 3931611648,
      "dividendYield": null,
      "beta": 1.32,
      "rsi": 29.4,
      "ma200": 59.69,
      "ma50": 59.62,
      "peRatio": 15.94,
      "forwardPE": 11.0,
      "priceToBook": 15.99,
      "week52High": 70.77,
      "week52Low": 35.61,
      "scores": {
        "dividendDaddy": 17,
        "moonShot": 88,
        "fallingKnife": 84,
        "overHyped": 5,
        "instWhale": 54
      }
    },
    {
      "symbol": "EEFT",
      "name": "Euronet Worldwide, Inc. - Common Stock",
      "exchange": "NASDAQ",
      "sector": "Technology",
      "industry": "Software - Infrastructure",
      "price": 66.01,
      "volume": 522244,
      "marketCap": 2775369472,
      "dividendYield": null,
      "beta": 0.82,
      "rsi": 29.5,
      "ma200": 82.88,
      "ma50": 70.8,
      "peRatio": 9.65,
      "forwardPE": 5.42,
      "priceToBook": 1.99,
      "week52High": 114.25,
      "week52Low": 64.34,
      "scores": {
        "dividendDaddy": 36,
        "moonShot": 70,
        "fallingKnife": 90,
        "overHyped": 5,
        "instWhale": 46
      }
    },
    {
      "symbol": "PGR",
      "name": "Progressive Corporation (The) Common Stock",
      "exchange": "NYSE",
      "sector": "Financial Services",
      "industry": "Insurance - Property & Casualty",
      "price": 193.36,
      "volume": 2542223,
      "marketCap": 113290854400,
      "dividendYield": 701.0,
      "beta": 0.29,
      "rsi": 29.6,
      "ma200": 218.41,
      "ma50": 205.43,
      "peRatio": 10.06,
      "forwardPE": 11.99,
      "priceToBook": 3.74,
      "week52High": 289.96,
      "week52Low": 192.02,
      "scores": {
        "dividendDaddy": 91,
        "moonShot": 36,
        "fallingKnife": 85,
        "overHyped": 6,
        "instWhale": 95
      }
    },
    {
      "symbol": "PG",
      "name": "Procter & Gamble Company (The) Common Stock",
      "exchange": "NYSE",
      "sector": "Consumer Defensive",
      "industry": "Household & Personal Products",
      "price": 144.09,
      "volume": 6524783,
      "marketCap": 337240522752,
      "dividendYield": 293.0,
      "beta": 0.34,
      "rsi": 29.7,
      "ma200": 150.68,
      "ma50": 153.52,
      "peRatio": 21.35,
      "forwardPE": 19.69,
      "priceToBook": 6.41,
      "week52High": 174.8,
      "week52Low": 137.62,
      "scores": {
        "dividendDaddy": 76,
        "moonShot": 39,
        "fallingKnife": 80,
        "overHyped": 6,
        "instWhale": 99
      }
    },
    {
      "symbol": "SPSC",
      "name": "SPS Commerce, Inc. - Common Stock",
      "exchange": "NASDAQ",
      "sector": "Technology",
      "industry": "Software - Application",
      "price": 56.23,
      "volume": 570873,
      "marketCap": 2120382464,
      "dividendYield": null,
      "beta": 0.63,
      "rsi": 29.7,
      "ma200": 96.74,
      "ma50": 67.04,
      "peRatio": 22.86,
      "forwardPE": 11.09,
      "priceToBook": 2.17,
      "week52High": 153.16,
      "week52Low": 52.56,
      "scores": {
        "dividendDaddy": 41,
        "moonShot": 57,
        "fallingKnife": 97,
        "overHyped": 6,
        "instWhale": 40
      }
    },
    {
      "symbol": "BSX",
      "name": "Boston Scientific Corporation Common Stock",
      "exchange": "NYSE",
      "sector": "Healthcare",
      "industry": "Medical Devices",
      "price": 62.0,
      "volume": 19476357,
      "marketCap": 92142854144,
      "dividendYield": null,
      "beta": 0.7,
      "rsi": 29.7,
      "ma200": 94.4,
      "ma50": 76.13,
      "peRatio": 31.96,
      "forwardPE": 15.86,
      "priceToBook": 3.79,
      "week52High": 109.5,
      "week52Low": 61.25,
      "scores": {
        "dividendDaddy": 40,
        "moonShot": 62,
        "fallingKnife": 96,
        "overHyped": 6,
        "instWhale": 94
      }
    },
    {
      "symbol": "ABT",
      "name": "Abbott Laboratories Common Stock",
      "exchange": "NYSE",
      "sector": "Healthcare",
      "industry": "Medical Devices",
      "price": 102.38,
      "volume": 7450652,
      "marketCap": 177903976448,
      "dividendYield": 245.0,
      "beta": 0.74,
      "rsi": 29.8,
      "ma200": 123.67,
      "ma50": 109.84,
      "peRatio": 27.52,
      "forwardPE": 16.77,
      "priceToBook": 3.41,
      "week52High": 139.06,
      "week52Low": 100.88,
      "scores": {
        "dividendDaddy": 70,
        "moonShot": 64,
        "fallingKnife": 89,
        "overHyped": 6,
        "instWhale": 97
      }
    },
    {
      "symbol": "SWIM",
      "name": "Latham Group, Inc. - Common Stock",
      "exchange": "NASDAQ",
      "sector": "Industrials",
      "industry": "Building Products & Equipment",
      "price": 5.36,
      "volume": 659730,
      "marketCap": 626902720,
      "dividendYield": null,
      "beta": 1.7,
      "rsi": 29.8,
      "ma200": 6.87,
      "ma50": 6.32,
      "peRatio": 59.56,
      "forwardPE": 19.68,
      "priceToBook": 1.54,
      "week52High": 8.97,
      "week52Low": 4.56,
      "scores": {
        "dividendDaddy": 10,
        "moonShot": 93,
        "fallingKnife": 91,
        "overHyped": 6,
        "instWhale": 17
      }
    },
    {
      "symbol": "HMC",
      "name": "Honda Motor Company, Ltd. Common Stock",
      "exchange": "NYSE",
      "sector": "Consumer Cyclical",
      "industry": "Auto Manufacturers",
      "price": 24.31,
      "volume": 1301519,
      "marketCap": 31897096192,
      "dividendYield": 571.0,
      "beta": 0.07,
      "rsi": 29.9,
      "ma200": 30.57,
      "ma50": 28.56,
      "peRatio": 10.39,
      "forwardPE": 4.9,
      "priceToBook": 1.2,
      "week52High": 34.89,
      "week52Low": 23.62,
      "scores": {
        "dividendDaddy": 88,
        "moonShot": 24,
        "fallingKnife": 90,
        "overHyped": 6,
        "instWhale": 87
      }
    },
    {
      "symbol": "CHEF",
      "name": "The Chefs' Warehouse, Inc. - Common Stock",
      "exchange": "NASDAQ",
      "sector": "Consumer Defensive",
      "industry": "Food Distribution",
      "price": 58.57,
      "volume": 447291,
      "marketCap": 2388345600,
      "dividendYield": null,
      "beta": 1.28,
      "rsi": 29.9,
      "ma200": 62.59,
      "ma50": 64.43,
      "peRatio": 34.86,
      "forwardPE": 23.61,
      "priceToBook": 3.94,
      "week52High": 73.94,
      "week52Low": 45.0,
      "scores": {
        "dividendDaddy": 18,
        "moonShot": 87,
        "fallingKnife": 82,
        "overHyped": 6,
        "instWhale": 43
      }
    },
    {
      "symbol": "UDR",
      "name": "UDR, Inc. Common Stock",
      "exchange": "NYSE",
      "sector": "Real Estate",
      "industry": "REIT - Residential",
      "price": 34.24,
      "volume": 2599066,
      "marketCap": 12890985472,
      "dividendYield": 515.0,
      "beta": 0.69,
      "rsi": 30.0,
      "ma200": 36.75,
      "ma50": 36.65,
      "peRatio": 30.3,
      "forwardPE": 62.25,
      "priceToBook": 3.46,
      "week52High": 45.56,
      "week52Low": 32.94,
      "scores": {
        "dividendDaddy": 87,
        "moonShot": 61,
        "fallingKnife": 82,
        "overHyped": 6,
        "instWhale": 77
      }
    }
  ]
}